{
"meta":{"test_sets":[],"test_metrics":[],"learn_metrics":[{"best_value":"Min","name":"RMSE"}],"launch_mode":"Train","parameters":"","iteration_count":1000,"learn_sets":["learn"],"name":"experiment"},
"iterations":[
{"learn":[14.59871775],"iteration":0,"passed_time":0.1410999031,"remaining_time":140.9588032},
{"learn":[14.22518863],"iteration":1,"passed_time":0.143437815,"remaining_time":71.57546969},
{"learn":[13.8866124],"iteration":2,"passed_time":0.1456113003,"remaining_time":48.3914888},
{"learn":[13.52356875],"iteration":3,"passed_time":0.1477975651,"remaining_time":36.80159372},
{"learn":[13.18870211],"iteration":4,"passed_time":0.149530226,"remaining_time":29.75651498},
{"learn":[12.9124226],"iteration":5,"passed_time":0.151591637,"remaining_time":25.11368119},
{"learn":[12.60003351],"iteration":6,"passed_time":0.1531766818,"remaining_time":21.72920643},
{"learn":[12.32990573],"iteration":7,"passed_time":0.1545873045,"remaining_time":19.16882575},
{"learn":[12.0660619],"iteration":8,"passed_time":0.1560008872,"remaining_time":17.17743102},
{"learn":[11.77309809],"iteration":9,"passed_time":0.1572018935,"remaining_time":15.56298746},
{"learn":[11.49227636],"iteration":10,"passed_time":0.1583566409,"remaining_time":14.23770162},
{"learn":[11.26264833],"iteration":11,"passed_time":0.1595183521,"remaining_time":13.13367766},
{"learn":[11.04260393],"iteration":12,"passed_time":0.1605710214,"remaining_time":12.19104601},
{"learn":[10.79916926],"iteration":13,"passed_time":0.1618344921,"remaining_time":11.39777209},
{"learn":[10.5541002],"iteration":14,"passed_time":0.1630058781,"remaining_time":10.70405266},
{"learn":[10.31918115],"iteration":15,"passed_time":0.1642751949,"remaining_time":10.10292449},
{"learn":[10.10004441],"iteration":16,"passed_time":0.1654170272,"remaining_time":9.564996338},
{"learn":[9.894556723],"iteration":17,"passed_time":0.1663316984,"remaining_time":9.074318214},
{"learn":[9.690174082],"iteration":18,"passed_time":0.1673474164,"remaining_time":8.640411341},
{"learn":[9.506034866],"iteration":19,"passed_time":0.168198265,"remaining_time":8.241714987},
{"learn":[9.338524633],"iteration":20,"passed_time":0.1687175488,"remaining_time":7.865451443},
{"learn":[9.170203312],"iteration":21,"passed_time":0.1692531858,"remaining_time":7.52407344},
{"learn":[9.010299969],"iteration":22,"passed_time":0.1697503834,"remaining_time":7.210701069},
{"learn":[8.843866678],"iteration":23,"passed_time":0.1702890106,"remaining_time":6.925086433},
{"learn":[8.690548059],"iteration":24,"passed_time":0.1707895767,"remaining_time":6.660793493},
{"learn":[8.555307687],"iteration":25,"passed_time":0.1712979564,"remaining_time":6.417084982},
{"learn":[8.413851302],"iteration":26,"passed_time":0.1718161678,"remaining_time":6.191745602},
{"learn":[8.29256019],"iteration":27,"passed_time":0.1723275164,"remaining_time":5.982226639},
{"learn":[8.162193833],"iteration":28,"passed_time":0.1728325668,"remaining_time":5.786911116},
{"learn":[8.040736294],"iteration":29,"passed_time":0.1733286639,"remaining_time":5.604293465},
{"learn":[7.921220278],"iteration":30,"passed_time":0.1738106218,"remaining_time":5.432983629},
{"learn":[7.809589039],"iteration":31,"passed_time":0.1743553955,"remaining_time":5.274250714},
{"learn":[7.699675801],"iteration":32,"passed_time":0.1748941048,"remaining_time":5.124927252},
{"learn":[7.60645267],"iteration":33,"passed_time":0.1753978756,"remaining_time":4.98336317},
{"learn":[7.498880302],"iteration":34,"passed_time":0.1759024644,"remaining_time":4.849882232},
{"learn":[7.401158744],"iteration":35,"passed_time":0.1764834552,"remaining_time":4.725834745},
{"learn":[7.306431077],"iteration":36,"passed_time":0.1771784664,"remaining_time":4.611428734},
{"learn":[7.223863468],"iteration":37,"passed_time":0.1777334843,"remaining_time":4.49946347},
{"learn":[7.143477682],"iteration":38,"passed_time":0.1783780108,"remaining_time":4.395417138},
{"learn":[7.062817131],"iteration":39,"passed_time":0.1789529597,"remaining_time":4.294871032},
{"learn":[6.990793435],"iteration":40,"passed_time":0.1795420391,"remaining_time":4.199532085},
{"learn":[6.931862224],"iteration":41,"passed_time":0.1801206386,"remaining_time":4.108465995},
{"learn":[6.858296558],"iteration":42,"passed_time":0.1807221594,"remaining_time":4.022118757},
{"learn":[6.786268161],"iteration":43,"passed_time":0.1814396756,"remaining_time":3.942189315},
{"learn":[6.717118549],"iteration":44,"passed_time":0.1819825093,"remaining_time":3.862073253},
{"learn":[6.652948106],"iteration":45,"passed_time":0.1825105599,"remaining_time":3.785110308},
{"learn":[6.589686076],"iteration":46,"passed_time":0.1830147559,"remaining_time":3.710916222},
{"learn":[6.531283097],"iteration":47,"passed_time":0.1835538555,"remaining_time":3.640484801},
{"learn":[6.471368031],"iteration":48,"passed_time":0.184058714,"remaining_time":3.572241573},
{"learn":[6.416481395],"iteration":49,"passed_time":0.1846259389,"remaining_time":3.507892839},
{"learn":[6.369870822],"iteration":50,"passed_time":0.1851913807,"remaining_time":3.446012162},
{"learn":[6.325678067],"iteration":51,"passed_time":0.1857018198,"remaining_time":3.385487023},
{"learn":[6.275766122],"iteration":52,"passed_time":0.1861945923,"remaining_time":3.326910923},
{"learn":[6.224773967],"iteration":53,"passed_time":0.1867265711,"remaining_time":3.271172894},
{"learn":[6.182249254],"iteration":54,"passed_time":0.1872356308,"remaining_time":3.217048565},
{"learn":[6.139904173],"iteration":55,"passed_time":0.1877693587,"remaining_time":3.165254904},
{"learn":[6.100525536],"iteration":56,"passed_time":0.1882662874,"remaining_time":3.114651035},
{"learn":[6.062568564],"iteration":57,"passed_time":0.188768552,"remaining_time":3.065861654},
{"learn":[6.030559288],"iteration":58,"passed_time":0.1893062984,"remaining_time":3.01927503},
{"learn":[5.997931376],"iteration":59,"passed_time":0.1898278565,"remaining_time":2.973969751},
{"learn":[5.964103835],"iteration":60,"passed_time":0.1903215572,"remaining_time":2.929703971},
{"learn":[5.933729724],"iteration":61,"passed_time":0.1908244429,"remaining_time":2.886989152},
{"learn":[5.901932711],"iteration":62,"passed_time":0.1913603677,"remaining_time":2.846105787},
{"learn":[5.873727795],"iteration":63,"passed_time":0.1919650048,"remaining_time":2.807488195},
{"learn":[5.846485734],"iteration":64,"passed_time":0.192655857,"remaining_time":2.771280404},
{"learn":[5.820630862],"iteration":65,"passed_time":0.1934403526,"remaining_time":2.737474081},
{"learn":[5.793646238],"iteration":66,"passed_time":0.1939767031,"remaining_time":2.70119797},
{"learn":[5.765388646],"iteration":67,"passed_time":0.1946327652,"remaining_time":2.667613782},
{"learn":[5.747073912],"iteration":68,"passed_time":0.1952809028,"remaining_time":2.634877108},
{"learn":[5.722315217],"iteration":69,"passed_time":0.1958472004,"remaining_time":2.601969948},
{"learn":[5.699970599],"iteration":70,"passed_time":0.196435383,"remaining_time":2.570260152},
{"learn":[5.682732647],"iteration":71,"passed_time":0.1969502402,"remaining_time":2.538469762},
{"learn":[5.663525791],"iteration":72,"passed_time":0.1974605838,"remaining_time":2.50747892},
{"learn":[5.642381613],"iteration":73,"passed_time":0.1980222572,"remaining_time":2.477954191},
{"learn":[5.621404779],"iteration":74,"passed_time":0.1985257943,"remaining_time":2.448484796},
{"learn":[5.602460129],"iteration":75,"passed_time":0.1990490519,"remaining_time":2.420017421},
{"learn":[5.587337574],"iteration":76,"passed_time":0.1995373222,"remaining_time":2.391856473},
{"learn":[5.572393026],"iteration":77,"passed_time":0.2000415429,"remaining_time":2.364593622},
{"learn":[5.558425806],"iteration":78,"passed_time":0.2005514394,"remaining_time":2.338074376},
{"learn":[5.541518902],"iteration":79,"passed_time":0.2010392277,"remaining_time":2.311951119},
{"learn":[5.526157283],"iteration":80,"passed_time":0.2015131141,"remaining_time":2.28630311},
{"learn":[5.511746977],"iteration":81,"passed_time":0.2020520878,"remaining_time":2.261997763},
{"learn":[5.504975022],"iteration":82,"passed_time":0.2023282052,"remaining_time":2.235361014},
{"learn":[5.493980522],"iteration":83,"passed_time":0.2028278248,"remaining_time":2.211789137},
{"learn":[5.480745463],"iteration":84,"passed_time":0.2033456434,"remaining_time":2.188956044},
{"learn":[5.464052013],"iteration":85,"passed_time":0.2038576366,"remaining_time":2.166579999},
{"learn":[5.449143727],"iteration":86,"passed_time":0.204350646,"remaining_time":2.144507354},
{"learn":[5.438255432],"iteration":87,"passed_time":0.204851952,"remaining_time":2.123011139},
{"learn":[5.425927931],"iteration":88,"passed_time":0.2053573474,"remaining_time":2.102028579},
{"learn":[5.412331217],"iteration":89,"passed_time":0.2060325486,"remaining_time":2.083217991},
{"learn":[5.400691499],"iteration":90,"passed_time":0.2066545416,"remaining_time":2.064274487},
{"learn":[5.391618744],"iteration":91,"passed_time":0.2072203644,"remaining_time":2.045174901},
{"learn":[5.380766572],"iteration":92,"passed_time":0.2078095059,"remaining_time":2.02670131},
{"learn":[5.372207183],"iteration":93,"passed_time":0.2083327532,"remaining_time":2.007973132},
{"learn":[5.362918837],"iteration":94,"passed_time":0.2088532574,"remaining_time":1.989602084},
{"learn":[5.348292324],"iteration":95,"passed_time":0.2093640466,"remaining_time":1.971511439},
{"learn":[5.339772295],"iteration":96,"passed_time":0.2098766916,"remaining_time":1.953800541},
{"learn":[5.331515983],"iteration":97,"passed_time":0.2104260785,"remaining_time":1.936778804},
{"learn":[5.323861644],"iteration":98,"passed_time":0.2109130737,"remaining_time":1.919522014},
{"learn":[5.313277281],"iteration":99,"passed_time":0.2114209739,"remaining_time":1.902788765},
{"learn":[5.30685627],"iteration":100,"passed_time":0.2119250847,"remaining_time":1.886343081},
{"learn":[5.29652059],"iteration":101,"passed_time":0.2124583089,"remaining_time":1.870466288},
{"learn":[5.288350766],"iteration":102,"passed_time":0.2129727027,"remaining_time":1.85472344},
{"learn":[5.27993346],"iteration":103,"passed_time":0.2134894,"remaining_time":1.839293293},
{"learn":[5.271789139],"iteration":104,"passed_time":0.214009748,"remaining_time":1.824178328},
{"learn":[5.262684686],"iteration":105,"passed_time":0.2145390462,"remaining_time":1.80941422},
{"learn":[5.251619772],"iteration":106,"passed_time":0.2150417089,"remaining_time":1.794693888},
{"learn":[5.241012171],"iteration":107,"passed_time":0.2155747155,"remaining_time":1.780487465},
{"learn":[5.232684032],"iteration":108,"passed_time":0.2160952094,"remaining_time":1.766429648},
{"learn":[5.224267141],"iteration":109,"passed_time":0.2166034392,"remaining_time":1.752518736},
{"learn":[5.216324968],"iteration":110,"passed_time":0.217129836,"remaining_time":1.738994812},
{"learn":[5.211102527],"iteration":111,"passed_time":0.2176126847,"remaining_time":1.725357714},
{"learn":[5.206364257],"iteration":112,"passed_time":0.2181193858,"remaining_time":1.712140666},
{"learn":[5.196937641],"iteration":113,"passed_time":0.2187155661,"remaining_time":1.699842031},
{"learn":[5.190746047],"iteration":114,"passed_time":0.2192821009,"remaining_time":1.687518777},
{"learn":[5.181885213],"iteration":115,"passed_time":0.2198636165,"remaining_time":1.675512388},
{"learn":[5.178293568],"iteration":116,"passed_time":0.2202924269,"remaining_time":1.662548829},
{"learn":[5.170991438],"iteration":117,"passed_time":0.2208671357,"remaining_time":1.650888252},
{"learn":[5.166257212],"iteration":118,"passed_time":0.2215029964,"remaining_time":1.639866721},
{"learn":[5.161421246],"iteration":119,"passed_time":0.2221185279,"remaining_time":1.628869205},
{"learn":[5.158223542],"iteration":120,"passed_time":0.2227393223,"remaining_time":1.618081523},
{"learn":[5.15470988],"iteration":121,"passed_time":0.2231436367,"remaining_time":1.605902566},
{"learn":[5.146388143],"iteration":122,"passed_time":0.2236798277,"remaining_time":1.594855357},
{"learn":[5.139529364],"iteration":123,"passed_time":0.2241739026,"remaining_time":1.583680151},
{"learn":[5.134276023],"iteration":124,"passed_time":0.224656141,"remaining_time":1.572592987},
{"learn":[5.128536065],"iteration":125,"passed_time":0.225164532,"remaining_time":1.561855564},
{"learn":[5.123300353],"iteration":126,"passed_time":0.2255880811,"remaining_time":1.550696022},
{"learn":[5.116200518],"iteration":127,"passed_time":0.2260992356,"remaining_time":1.540301042},
{"learn":[5.108728704],"iteration":128,"passed_time":0.2266267372,"remaining_time":1.530169675},
{"learn":[5.104075866],"iteration":129,"passed_time":0.2271230675,"remaining_time":1.519977452},
{"learn":[5.100317606],"iteration":130,"passed_time":0.2277327034,"remaining_time":1.51068488},
{"learn":[5.095814182],"iteration":131,"passed_time":0.2288096107,"remaining_time":1.504596531},
{"learn":[5.092146915],"iteration":132,"passed_time":0.2293720258,"remaining_time":1.495229672},
{"learn":[5.085258329],"iteration":133,"passed_time":0.2299203892,"remaining_time":1.485903411},
{"learn":[5.079219421],"iteration":134,"passed_time":0.2304568877,"remaining_time":1.476631169},
{"learn":[5.076476829],"iteration":135,"passed_time":0.2309729125,"remaining_time":1.467357327},
{"learn":[5.072133867],"iteration":136,"passed_time":0.231527914,"remaining_time":1.458456859},
{"learn":[5.067031564],"iteration":137,"passed_time":0.2321530253,"remaining_time":1.450115274},
{"learn":[5.061358312],"iteration":138,"passed_time":0.2326975729,"remaining_time":1.441385685},
{"learn":[5.056759124],"iteration":139,"passed_time":0.2332646261,"remaining_time":1.432911275},
{"learn":[5.050254],"iteration":140,"passed_time":0.2337929596,"remaining_time":1.424313137},
{"learn":[5.048376474],"iteration":141,"passed_time":0.2341299871,"remaining_time":1.414672739},
{"learn":[5.042603751],"iteration":142,"passed_time":0.2346595813,"remaining_time":1.406316512},
{"learn":[5.037477349],"iteration":143,"passed_time":0.2351876847,"remaining_time":1.398060126},
{"learn":[5.03230489],"iteration":144,"passed_time":0.2357139002,"remaining_time":1.389899205},
{"learn":[5.025976187],"iteration":145,"passed_time":0.2362086284,"remaining_time":1.38165869},
{"learn":[5.01952451],"iteration":146,"passed_time":0.2368122245,"remaining_time":1.374155289},
{"learn":[5.017569424],"iteration":147,"passed_time":0.2373332021,"remaining_time":1.366269515},
{"learn":[5.008962367],"iteration":148,"passed_time":0.2378526661,"remaining_time":1.358473952},
{"learn":[5.003880266],"iteration":149,"passed_time":0.2383699114,"remaining_time":1.350762831},
{"learn":[4.996387564],"iteration":150,"passed_time":0.2388992384,"remaining_time":1.343214923},
{"learn":[4.993361683],"iteration":151,"passed_time":0.2394332254,"remaining_time":1.335785363},
{"learn":[4.99005752],"iteration":152,"passed_time":0.2399444409,"remaining_time":1.328319879},
{"learn":[4.986908764],"iteration":153,"passed_time":0.2404157562,"remaining_time":1.320725518},
{"learn":[4.985207175],"iteration":154,"passed_time":0.2409133584,"remaining_time":1.313366373},
{"learn":[4.979003494],"iteration":155,"passed_time":0.2414394204,"remaining_time":1.306249172},
{"learn":[4.973142217],"iteration":156,"passed_time":0.2419579822,"remaining_time":1.299175662},
{"learn":[4.967056696],"iteration":157,"passed_time":0.2424753177,"remaining_time":1.292178592},
{"learn":[4.961460696],"iteration":158,"passed_time":0.2429783743,"remaining_time":1.285187502},
{"learn":[4.954240363],"iteration":159,"passed_time":0.24347473,"remaining_time":1.278242333},
{"learn":[4.952320707],"iteration":160,"passed_time":0.2437928831,"remaining_time":1.270448627},
{"learn":[4.948337777],"iteration":161,"passed_time":0.244463018,"remaining_time":1.264567958},
{"learn":[4.943228639],"iteration":162,"passed_time":0.2449904372,"remaining_time":1.25801838},
{"learn":[4.938545759],"iteration":163,"passed_time":0.2455297473,"remaining_time":1.251602858},
{"learn":[4.935330572],"iteration":164,"passed_time":0.246086876,"remaining_time":1.245348736},
{"learn":[4.932051543],"iteration":165,"passed_time":0.2466682692,"remaining_time":1.23928516},
{"learn":[4.928964153],"iteration":166,"passed_time":0.2471893307,"remaining_time":1.232986302},
{"learn":[4.922860227],"iteration":167,"passed_time":0.2477837932,"remaining_time":1.227119738},
{"learn":[4.917668772],"iteration":168,"passed_time":0.2484000571,"remaining_time":1.221422766},
{"learn":[4.910365386],"iteration":169,"passed_time":0.2489914123,"remaining_time":1.215663954},
{"learn":[4.906457206],"iteration":170,"passed_time":0.2495074232,"remaining_time":1.209600315},
{"learn":[4.901996508],"iteration":171,"passed_time":0.2501962409,"remaining_time":1.204433067},
{"learn":[4.896816173],"iteration":172,"passed_time":0.2508732797,"remaining_time":1.199261285},
{"learn":[4.891123132],"iteration":173,"passed_time":0.2513987513,"remaining_time":1.193421658},
{"learn":[4.887630202],"iteration":174,"passed_time":0.2520161651,"remaining_time":1.188076207},
{"learn":[4.885259712],"iteration":175,"passed_time":0.2525808131,"remaining_time":1.182537443},
{"learn":[4.880659728],"iteration":176,"passed_time":0.2531334917,"remaining_time":1.17699923},
{"learn":[4.877299723],"iteration":177,"passed_time":0.2537511766,"remaining_time":1.171817231},
{"learn":[4.874038772],"iteration":178,"passed_time":0.2542926999,"remaining_time":1.166336909},
{"learn":[4.86943698],"iteration":179,"passed_time":0.2548347716,"remaining_time":1.160913959},
{"learn":[4.861268711],"iteration":180,"passed_time":0.2554366891,"remaining_time":1.155815737},
{"learn":[4.858673056],"iteration":181,"passed_time":0.2559861552,"remaining_time":1.150531181},
{"learn":[4.854036207],"iteration":182,"passed_time":0.2565228577,"remaining_time":1.145241392},
{"learn":[4.85130244],"iteration":183,"passed_time":0.2571199106,"remaining_time":1.140270908},
{"learn":[4.847510084],"iteration":184,"passed_time":0.257584368,"remaining_time":1.134763567},
{"learn":[4.845691673],"iteration":185,"passed_time":0.2581036515,"remaining_time":1.129550389},
{"learn":[4.842058646],"iteration":186,"passed_time":0.2586186307,"remaining_time":1.124368699},
{"learn":[4.838623675],"iteration":187,"passed_time":0.2591273639,"remaining_time":1.119209678},
{"learn":[4.834602161],"iteration":188,"passed_time":0.2596567809,"remaining_time":1.11418862},
{"learn":[4.830858976],"iteration":189,"passed_time":0.2601737525,"remaining_time":1.109161787},
{"learn":[4.827590511],"iteration":190,"passed_time":0.2606790984,"remaining_time":1.104132935},
{"learn":[4.822246226],"iteration":191,"passed_time":0.2611833968,"remaining_time":1.099146795},
{"learn":[4.816686395],"iteration":192,"passed_time":0.2616885486,"remaining_time":1.094210667},
{"learn":[4.814797121],"iteration":193,"passed_time":0.2621951869,"remaining_time":1.089326395},
{"learn":[4.811639392],"iteration":194,"passed_time":0.2627393171,"remaining_time":1.084641796},
{"learn":[4.804813432],"iteration":195,"passed_time":0.2633471902,"remaining_time":1.080260923},
{"learn":[4.80251613],"iteration":196,"passed_time":0.2639143059,"remaining_time":1.075752221},
{"learn":[4.800087884],"iteration":197,"passed_time":0.264454374,"remaining_time":1.071173778},
{"learn":[4.794773135],"iteration":198,"passed_time":0.2650321369,"remaining_time":1.066787647},
{"learn":[4.791664833],"iteration":199,"passed_time":0.2655937062,"remaining_time":1.062374825},
{"learn":[4.785989873],"iteration":200,"passed_time":0.2661464248,"remaining_time":1.057965141},
{"learn":[4.782387142],"iteration":201,"passed_time":0.2666575932,"remaining_time":1.053429502},
{"learn":[4.778623704],"iteration":202,"passed_time":0.2672527185,"remaining_time":1.049263136},
{"learn":[4.775772178],"iteration":203,"passed_time":0.2678275025,"remaining_time":1.045052412},
{"learn":[4.77023101],"iteration":204,"passed_time":0.2684100395,"remaining_time":1.040907226},
{"learn":[4.764496689],"iteration":205,"passed_time":0.2689875951,"remaining_time":1.03677743},
{"learn":[4.763138716],"iteration":206,"passed_time":0.2695343638,"remaining_time":1.032564012},
{"learn":[4.758053283],"iteration":207,"passed_time":0.2700685231,"remaining_time":1.028337838},
{"learn":[4.755063788],"iteration":208,"passed_time":0.2706522698,"remaining_time":1.024334667},
{"learn":[4.752465267],"iteration":209,"passed_time":0.2712764208,"remaining_time":1.020516059},
{"learn":[4.748067377],"iteration":210,"passed_time":0.2718739535,"remaining_time":1.016628196},
{"learn":[4.744163298],"iteration":211,"passed_time":0.2724037672,"remaining_time":1.012519663},
{"learn":[4.736670896],"iteration":212,"passed_time":0.2729303943,"remaining_time":1.008432959},
{"learn":[4.73349255],"iteration":213,"passed_time":0.2734479686,"remaining_time":1.004346277},
{"learn":[4.731864595],"iteration":214,"passed_time":0.2739701167,"remaining_time":1.000309496},
{"learn":[4.728398311],"iteration":215,"passed_time":0.2744720285,"remaining_time":0.9962318071},
{"learn":[4.723865975],"iteration":216,"passed_time":0.2750076437,"remaining_time":0.9923086866},
{"learn":[4.723483365],"iteration":217,"passed_time":0.2755019195,"remaining_time":0.9882683534},
{"learn":[4.72095416],"iteration":218,"passed_time":0.2760217391,"remaining_time":0.9843514989},
{"learn":[4.716173382],"iteration":219,"passed_time":0.2765750578,"remaining_time":0.9805842957},
{"learn":[4.710563974],"iteration":220,"passed_time":0.2770922075,"remaining_time":0.976718686},
{"learn":[4.707160263],"iteration":221,"passed_time":0.2776350119,"remaining_time":0.9729731498},
{"learn":[4.70408351],"iteration":222,"passed_time":0.2781431411,"remaining_time":0.9691355186},
{"learn":[4.702501831],"iteration":223,"passed_time":0.2786599715,"remaining_time":0.9653577585},
{"learn":[4.700269738],"iteration":224,"passed_time":0.2791656342,"remaining_time":0.9615705177},
{"learn":[4.695346302],"iteration":225,"passed_time":0.2797248524,"remaining_time":0.9579957335},
{"learn":[4.689769299],"iteration":226,"passed_time":0.2802266086,"remaining_time":0.9542518435},
{"learn":[4.687919514],"iteration":227,"passed_time":0.2807457187,"remaining_time":0.9505951527},
{"learn":[4.682982074],"iteration":228,"passed_time":0.2812862702,"remaining_time":0.9470380539},
{"learn":[4.679578702],"iteration":229,"passed_time":0.2817970783,"remaining_time":0.94340761},
{"learn":[4.675751423],"iteration":230,"passed_time":0.2823594385,"remaining_time":0.939975793},
{"learn":[4.672710726],"iteration":231,"passed_time":0.2830728331,"remaining_time":0.9370686889},
{"learn":[4.6690533],"iteration":232,"passed_time":0.2836395328,"remaining_time":0.9336975178},
{"learn":[4.667595702],"iteration":233,"passed_time":0.2841719354,"remaining_time":0.930238045},
{"learn":[4.664241291],"iteration":234,"passed_time":0.2846848094,"remaining_time":0.9267399116},
{"learn":[4.662246999],"iteration":235,"passed_time":0.2851949882,"remaining_time":0.9232583517},
{"learn":[4.658668443],"iteration":236,"passed_time":0.2857139367,"remaining_time":0.9198300999},
{"learn":[4.658017572],"iteration":237,"passed_time":0.2861907987,"remaining_time":0.9162915488},
{"learn":[4.657656705],"iteration":238,"passed_time":0.286664312,"remaining_time":0.9127679556},
{"learn":[4.653242871],"iteration":239,"passed_time":0.2871630875,"remaining_time":0.9093497771},
{"learn":[4.6507302],"iteration":240,"passed_time":0.2876541661,"remaining_time":0.9059315855},
{"learn":[4.647671336],"iteration":241,"passed_time":0.2881672071,"remaining_time":0.902606376},
{"learn":[4.645506007],"iteration":242,"passed_time":0.2886984321,"remaining_time":0.8993609593},
{"learn":[4.641297906],"iteration":243,"passed_time":0.2891863653,"remaining_time":0.8960036563},
{"learn":[4.63798107],"iteration":244,"passed_time":0.2896986635,"remaining_time":0.8927448609},
{"learn":[4.635062318],"iteration":245,"passed_time":0.2901860968,"remaining_time":0.8894321829},
{"learn":[4.631606017],"iteration":246,"passed_time":0.2908082372,"remaining_time":0.8865530469},
{"learn":[4.630215494],"iteration":247,"passed_time":0.2913496589,"remaining_time":0.8834473526},
{"learn":[4.62729814],"iteration":248,"passed_time":0.2918813055,"remaining_time":0.8803327729},
{"learn":[4.624691756],"iteration":249,"passed_time":0.2923940097,"remaining_time":0.8771820292},
{"learn":[4.621840053],"iteration":250,"passed_time":0.2929228513,"remaining_time":0.8741004605},
{"learn":[4.619602091],"iteration":251,"passed_time":0.2934263477,"remaining_time":0.870963921},
{"learn":[4.613584029],"iteration":252,"passed_time":0.2939261992,"remaining_time":0.8678374341},
{"learn":[4.6119388],"iteration":253,"passed_time":0.2943986704,"remaining_time":0.864651213},
{"learn":[4.60870702],"iteration":254,"passed_time":0.2948981666,"remaining_time":0.8615652318},
{"learn":[4.604771557],"iteration":255,"passed_time":0.2954083824,"remaining_time":0.8585306115},
{"learn":[4.604231277],"iteration":256,"passed_time":0.2959191481,"remaining_time":0.8555172257},
{"learn":[4.600750354],"iteration":257,"passed_time":0.2964234583,"remaining_time":0.8525046745},
{"learn":[4.596488253],"iteration":258,"passed_time":0.2969113832,"remaining_time":0.8494646137},
{"learn":[4.59470784],"iteration":259,"passed_time":0.2974306748,"remaining_time":0.8465334592},
{"learn":[4.588818005],"iteration":260,"passed_time":0.298092146,"remaining_time":0.844023356},
{"learn":[4.585054174],"iteration":261,"passed_time":0.2988047722,"remaining_time":0.8416714576},
{"learn":[4.581471435],"iteration":262,"passed_time":0.2993958213,"remaining_time":0.8389913319},
{"learn":[4.577555199],"iteration":263,"passed_time":0.2999292086,"remaining_time":0.8361662784},
{"learn":[4.57457145],"iteration":264,"passed_time":0.3004184089,"remaining_time":0.8332359643},
{"learn":[4.573029224],"iteration":265,"passed_time":0.3009152091,"remaining_time":0.8303449755},
{"learn":[4.571326203],"iteration":266,"passed_time":0.3014365467,"remaining_time":0.8275392837},
{"learn":[4.571019224],"iteration":267,"passed_time":0.3019375523,"remaining_time":0.8246951056},
{"learn":[4.565766631],"iteration":268,"passed_time":0.3024287579,"remaining_time":0.8218417177},
{"learn":[4.563383471],"iteration":269,"passed_time":0.3029557205,"remaining_time":0.8191025035},
{"learn":[4.558165805],"iteration":270,"passed_time":0.3034633021,"remaining_time":0.8163274805},
{"learn":[4.55629209],"iteration":271,"passed_time":0.3039608154,"remaining_time":0.8135421825},
{"learn":[4.549383848],"iteration":272,"passed_time":0.3045175703,"remaining_time":0.8109314052},
{"learn":[4.546227503],"iteration":273,"passed_time":0.3050421733,"remaining_time":0.8082504299},
{"learn":[4.540620977],"iteration":274,"passed_time":0.3055728635,"remaining_time":0.8056011856},
{"learn":[4.532898237],"iteration":275,"passed_time":0.306096175,"remaining_time":0.8029479373},
{"learn":[4.529757367],"iteration":276,"passed_time":0.3066170888,"remaining_time":0.8003038094},
{"learn":[4.52579294],"iteration":277,"passed_time":0.3071108135,"remaining_time":0.7976043428},
{"learn":[4.521572155],"iteration":278,"passed_time":0.307628311,"remaining_time":0.7949821226},
{"learn":[4.518818099],"iteration":279,"passed_time":0.3081355751,"remaining_time":0.7923486217},
{"learn":[4.514012334],"iteration":280,"passed_time":0.3086358576,"remaining_time":0.78971239},
{"learn":[4.508331416],"iteration":281,"passed_time":0.3091448376,"remaining_time":0.7871134519},
{"learn":[4.506038537],"iteration":282,"passed_time":0.3096531303,"remaining_time":0.784527542},
{"learn":[4.505805643],"iteration":283,"passed_time":0.3101198288,"remaining_time":0.7818513994},
{"learn":[4.501550352],"iteration":284,"passed_time":0.3106247929,"remaining_time":0.7792867612},
{"learn":[4.494692643],"iteration":285,"passed_time":0.3111271371,"remaining_time":0.7767299856},
{"learn":[4.489330245],"iteration":286,"passed_time":0.3116430003,"remaining_time":0.7742211123},
{"learn":[4.484826955],"iteration":287,"passed_time":0.3121499259,"remaining_time":0.7717039834},
{"learn":[4.478285428],"iteration":288,"passed_time":0.3126670956,"remaining_time":0.7692259687},
{"learn":[4.475311671],"iteration":289,"passed_time":0.3132948059,"remaining_time":0.767032111},
{"learn":[4.471581298],"iteration":290,"passed_time":0.3140421651,"remaining_time":0.7651405328},
{"learn":[4.469164956],"iteration":291,"passed_time":0.3148082809,"remaining_time":0.7633022701},
{"learn":[4.462068024],"iteration":292,"passed_time":0.3154859136,"remaining_time":0.7612578189},
{"learn":[4.458540976],"iteration":293,"passed_time":0.3161455943,"remaining_time":0.7591795563},
{"learn":[4.455757458],"iteration":294,"passed_time":0.3168756353,"remaining_time":0.7572790607},
{"learn":[4.453027414],"iteration":295,"passed_time":0.3177043076,"remaining_time":0.7556210558},
{"learn":[4.450659338],"iteration":296,"passed_time":0.3186041072,"remaining_time":0.7541369945},
{"learn":[4.444696901],"iteration":297,"passed_time":0.3193141273,"remaining_time":0.7522097899},
{"learn":[4.442052813],"iteration":298,"passed_time":0.3200094739,"remaining_time":0.7502563251},
{"learn":[4.440036756],"iteration":299,"passed_time":0.3206931454,"remaining_time":0.7482840059},
{"learn":[4.435017051],"iteration":300,"passed_time":0.3213662431,"remaining_time":0.7462956942},
{"learn":[4.429962125],"iteration":301,"passed_time":0.3220643388,"remaining_time":0.7443738692},
{"learn":[4.427666256],"iteration":302,"passed_time":0.3227859694,"remaining_time":0.7425142597},
{"learn":[4.425030004],"iteration":303,"passed_time":0.3234948273,"remaining_time":0.740632894},
{"learn":[4.422588771],"iteration":304,"passed_time":0.3241816571,"remaining_time":0.7387090219},
{"learn":[4.418936667],"iteration":305,"passed_time":0.3248142981,"remaining_time":0.7366703362},
{"learn":[4.416887976],"iteration":306,"passed_time":0.3254078198,"remaining_time":0.7345525053},
{"learn":[4.413773354],"iteration":307,"passed_time":0.3259382649,"remaining_time":0.732302855},
{"learn":[4.411129391],"iteration":308,"passed_time":0.3264652738,"remaining_time":0.7300566479},
{"learn":[4.40850819],"iteration":309,"passed_time":0.3269835473,"remaining_time":0.7278020891},
{"learn":[4.404880292],"iteration":310,"passed_time":0.3274943179,"remaining_time":0.7255420741},
{"learn":[4.404593827],"iteration":311,"passed_time":0.3279792979,"remaining_time":0.7232364004},
{"learn":[4.402139942],"iteration":312,"passed_time":0.3285954512,"remaining_time":0.7212302715},
{"learn":[4.400284725],"iteration":313,"passed_time":0.329228988,"remaining_time":0.7192709738},
{"learn":[4.395805521],"iteration":314,"passed_time":0.3298529375,"remaining_time":0.7172992449},
{"learn":[4.392838833],"iteration":315,"passed_time":0.3304471149,"remaining_time":0.7152716031},
{"learn":[4.389213061],"iteration":316,"passed_time":0.3309589322,"remaining_time":0.7130755543},
{"learn":[4.3861981],"iteration":317,"passed_time":0.3315333602,"remaining_time":0.7110243763},
{"learn":[4.385054234],"iteration":318,"passed_time":0.3321286386,"remaining_time":0.7090269683},
{"learn":[4.379364607],"iteration":319,"passed_time":0.3327631828,"remaining_time":0.7071217635},
{"learn":[4.378387619],"iteration":320,"passed_time":0.3332752099,"remaining_time":0.7049653195},
{"learn":[4.375816727],"iteration":321,"passed_time":0.3338715254,"remaining_time":0.7029965659},
{"learn":[4.374600202],"iteration":322,"passed_time":0.3344921478,"remaining_time":0.7010872571},
{"learn":[4.37098897],"iteration":323,"passed_time":0.3350932712,"remaining_time":0.6991452201},
{"learn":[4.367418484],"iteration":324,"passed_time":0.3357293441,"remaining_time":0.6972840224},
{"learn":[4.363584638],"iteration":325,"passed_time":0.3363434925,"remaining_time":0.6953850121},
{"learn":[4.360770706],"iteration":326,"passed_time":0.3370114965,"remaining_time":0.6936047008},
{"learn":[4.358675808],"iteration":327,"passed_time":0.3375612737,"remaining_time":0.691588951},
{"learn":[4.354228195],"iteration":328,"passed_time":0.3381065244,"remaining_time":0.689572881},
{"learn":[4.353773425],"iteration":329,"passed_time":0.3385818107,"remaining_time":0.6874236762},
{"learn":[4.351648009],"iteration":330,"passed_time":0.3390755685,"remaining_time":0.6853219194},
{"learn":[4.348209927],"iteration":331,"passed_time":0.3395747686,"remaining_time":0.6832407994},
{"learn":[4.345852733],"iteration":332,"passed_time":0.3401344874,"remaining_time":0.6812903996},
{"learn":[4.34237339],"iteration":333,"passed_time":0.3407232678,"remaining_time":0.6794062766},
{"learn":[4.340814362],"iteration":334,"passed_time":0.3412438673,"remaining_time":0.6773945426},
{"learn":[4.339707068],"iteration":335,"passed_time":0.3417606671,"remaining_time":0.6753841754},
{"learn":[4.335430786],"iteration":336,"passed_time":0.3422942206,"remaining_time":0.6734156327},
{"learn":[4.33521887],"iteration":337,"passed_time":0.342762811,"remaining_time":0.6713283458},
{"learn":[4.328507238],"iteration":338,"passed_time":0.3433498937,"remaining_time":0.6694816511},
{"learn":[4.326140732],"iteration":339,"passed_time":0.3440300904,"remaining_time":0.6678231167},
{"learn":[4.323785636],"iteration":340,"passed_time":0.3446741928,"remaining_time":0.6661005661},
{"learn":[4.320632534],"iteration":341,"passed_time":0.3452089364,"remaining_time":0.6641739186},
{"learn":[4.31973724],"iteration":342,"passed_time":0.3457019704,"remaining_time":0.6621754943},
{"learn":[4.318000924],"iteration":343,"passed_time":0.3462172364,"remaining_time":0.6602282183},
{"learn":[4.312713628],"iteration":344,"passed_time":0.3467296699,"remaining_time":0.658283866},
{"learn":[4.308220789],"iteration":345,"passed_time":0.3472344728,"remaining_time":0.6563333676},
{"learn":[4.305890947],"iteration":346,"passed_time":0.3477495123,"remaining_time":0.6544104655},
{"learn":[4.305137856],"iteration":347,"passed_time":0.348242416,"remaining_time":0.6524541818},
{"learn":[4.304787172],"iteration":348,"passed_time":0.3489230534,"remaining_time":0.6508564692},
{"learn":[4.30350134],"iteration":349,"passed_time":0.3494797829,"remaining_time":0.6490338825},
{"learn":[4.30293809],"iteration":350,"passed_time":0.3500589521,"remaining_time":0.6472599998},
{"learn":[4.299548459],"iteration":351,"passed_time":0.3506505378,"remaining_time":0.6455157627},
{"learn":[4.294768408],"iteration":352,"passed_time":0.3512598536,"remaining_time":0.6438105532},
{"learn":[4.294581479],"iteration":353,"passed_time":0.3518165535,"remaining_time":0.6420155186},
{"learn":[4.292551604],"iteration":354,"passed_time":0.3523258404,"remaining_time":0.6401413157},
{"learn":[4.288628894],"iteration":355,"passed_time":0.3528788258,"remaining_time":0.638353831},
{"learn":[4.287802767],"iteration":356,"passed_time":0.3533866176,"remaining_time":0.6364918631},
{"learn":[4.284566905],"iteration":357,"passed_time":0.3539487612,"remaining_time":0.6347349293},
{"learn":[4.27890232],"iteration":358,"passed_time":0.3544576935,"remaining_time":0.6328896421},
{"learn":[4.276938023],"iteration":359,"passed_time":0.3549515862,"remaining_time":0.6310250421},
{"learn":[4.273425094],"iteration":360,"passed_time":0.3554654855,"remaining_time":0.6292034494},
{"learn":[4.269726505],"iteration":361,"passed_time":0.3559849708,"remaining_time":0.6273989265},
{"learn":[4.265565857],"iteration":362,"passed_time":0.3564922439,"remaining_time":0.6255800533},
{"learn":[4.262117173],"iteration":363,"passed_time":0.3570052256,"remaining_time":0.6237783613},
{"learn":[4.259185148],"iteration":364,"passed_time":0.3575452471,"remaining_time":0.6220307723},
{"learn":[4.257668507],"iteration":365,"passed_time":0.3580734193,"remaining_time":0.6202692564},
{"learn":[4.253432436],"iteration":366,"passed_time":0.3586730023,"remaining_time":0.6186376306},
{"learn":[4.250216667],"iteration":367,"passed_time":0.3592641441,"remaining_time":0.616997117},
{"learn":[4.24514828],"iteration":368,"passed_time":0.3599076607,"remaining_time":0.6154518533},
{"learn":[4.244015772],"iteration":369,"passed_time":0.3604693508,"remaining_time":0.6137721379},
{"learn":[4.240329192],"iteration":370,"passed_time":0.3610513206,"remaining_time":0.6121328319},
{"learn":[4.236718014],"iteration":371,"passed_time":0.3615926784,"remaining_time":0.6104306506},
{"learn":[4.233495944],"iteration":372,"passed_time":0.3621696393,"remaining_time":0.6087945412},
{"learn":[4.230357491],"iteration":373,"passed_time":0.3627920929,"remaining_time":0.6072402411},
{"learn":[4.227381215],"iteration":374,"passed_time":0.3633408191,"remaining_time":0.6055680318},
{"learn":[4.226169067],"iteration":375,"passed_time":0.3639060721,"remaining_time":0.6039292261},
{"learn":[4.225963861],"iteration":376,"passed_time":0.3643958565,"remaining_time":0.6021714021},
{"learn":[4.224346548],"iteration":377,"passed_time":0.3648933038,"remaining_time":0.6004328968},
{"learn":[4.222595381],"iteration":378,"passed_time":0.365398852,"remaining_time":0.5987142139},
{"learn":[4.219700938],"iteration":379,"passed_time":0.3659123036,"remaining_time":0.5970148111},
{"learn":[4.216356207],"iteration":380,"passed_time":0.3664420006,"remaining_time":0.5953480272},
{"learn":[4.214326494],"iteration":381,"passed_time":0.366957212,"remaining_time":0.5936637619},
{"learn":[4.212901398],"iteration":382,"passed_time":0.3674914662,"remaining_time":0.5920162785},
{"learn":[4.211331091],"iteration":383,"passed_time":0.3679693725,"remaining_time":0.5902842017},
{"learn":[4.208624791],"iteration":384,"passed_time":0.368502469,"remaining_time":0.5886468011},
{"learn":[4.204659106],"iteration":385,"passed_time":0.3690014857,"remaining_time":0.5869609125},
{"learn":[4.202968852],"iteration":386,"passed_time":0.3694997832,"remaining_time":0.5852800184},
{"learn":[4.197261935],"iteration":387,"passed_time":0.370016101,"remaining_time":0.5836336438},
{"learn":[4.196934403],"iteration":388,"passed_time":0.3705475561,"remaining_time":0.5820168554},
{"learn":[4.192479929],"iteration":389,"passed_time":0.3710744586,"remaining_time":0.5803985122},
{"learn":[4.190243116],"iteration":390,"passed_time":0.3716062487,"remaining_time":0.5787933644},
{"learn":[4.185852431],"iteration":391,"passed_time":0.3721356325,"remaining_time":0.5771899607},
{"learn":[4.180967944],"iteration":392,"passed_time":0.3726604663,"remaining_time":0.575584995},
{"learn":[4.178283162],"iteration":393,"passed_time":0.3731833376,"remaining_time":0.5739824939},
{"learn":[4.176341157],"iteration":394,"passed_time":0.3736912617,"remaining_time":0.5723625654},
{"learn":[4.176041504],"iteration":395,"passed_time":0.3743353091,"remaining_time":0.5709558755},
{"learn":[4.175564513],"iteration":396,"passed_time":0.3750468276,"remaining_time":0.5696555089},
{"learn":[4.170830274],"iteration":397,"passed_time":0.3755989079,"remaining_time":0.5681169412},
{"learn":[4.167804808],"iteration":398,"passed_time":0.3761001244,"remaining_time":0.5665067036},
{"learn":[4.165860548],"iteration":399,"passed_time":0.3766369696,"remaining_time":0.5649554545},
{"learn":[4.160950571],"iteration":400,"passed_time":0.3771651137,"remaining_time":0.5633962671},
{"learn":[4.158544115],"iteration":401,"passed_time":0.3776604381,"remaining_time":0.561793388},
{"learn":[4.154448767],"iteration":402,"passed_time":0.3782460998,"remaining_time":0.5603298302},
{"learn":[4.15197457],"iteration":403,"passed_time":0.3787826197,"remaining_time":0.5587981222},
{"learn":[4.149562679],"iteration":404,"passed_time":0.3793436235,"remaining_time":0.5573072987},
{"learn":[4.149327961],"iteration":405,"passed_time":0.3798852014,"remaining_time":0.5557926346},
{"learn":[4.147444889],"iteration":406,"passed_time":0.3804494781,"remaining_time":0.5543158243},
{"learn":[4.147254809],"iteration":407,"passed_time":0.3809566358,"remaining_time":0.5527606089},
{"learn":[4.144589165],"iteration":408,"passed_time":0.3815399862,"remaining_time":0.5513206158},
{"learn":[4.141691034],"iteration":409,"passed_time":0.3821178968,"remaining_time":0.5498769735},
{"learn":[4.138893468],"iteration":410,"passed_time":0.3826406008,"remaining_time":0.5483584279},
{"learn":[4.136964597],"iteration":411,"passed_time":0.3831750494,"remaining_time":0.5468614783},
{"learn":[4.133773523],"iteration":412,"passed_time":0.3836798494,"remaining_time":0.5453270499},
{"learn":[4.131363444],"iteration":413,"passed_time":0.3846338853,"remaining_time":0.5444334706},
{"learn":[4.130228592],"iteration":414,"passed_time":0.3853335358,"remaining_time":0.5431810082},
{"learn":[4.12884186],"iteration":415,"passed_time":0.3858609043,"remaining_time":0.5416893464},
{"learn":[4.12413494],"iteration":416,"passed_time":0.3864495206,"remaining_time":0.5402879389},
{"learn":[4.119422508],"iteration":417,"passed_time":0.3870277976,"remaining_time":0.5388760245},
{"learn":[4.117038244],"iteration":418,"passed_time":0.3875468881,"remaining_time":0.537386019},
{"learn":[4.116067631],"iteration":419,"passed_time":0.3880772451,"remaining_time":0.5359161956},
{"learn":[4.110343455],"iteration":420,"passed_time":0.3886465494,"remaining_time":0.5345043993},
{"learn":[4.105604544],"iteration":421,"passed_time":0.3891779414,"remaining_time":0.5330446685},
{"learn":[4.103390131],"iteration":422,"passed_time":0.3898336735,"remaining_time":0.5317589352},
{"learn":[4.096724402],"iteration":423,"passed_time":0.3907684038,"remaining_time":0.53085519},
{"learn":[4.093431279],"iteration":424,"passed_time":0.3916817272,"remaining_time":0.5299223368},
{"learn":[4.091412744],"iteration":425,"passed_time":0.3924477681,"remaining_time":0.5287911241},
{"learn":[4.091192901],"iteration":426,"passed_time":0.3933126538,"remaining_time":0.5277942638},
{"learn":[4.088994581],"iteration":427,"passed_time":0.3941953989,"remaining_time":0.5268218883},
{"learn":[4.087845355],"iteration":428,"passed_time":0.3948171169,"remaining_time":0.5255025029},
{"learn":[4.083650279],"iteration":429,"passed_time":0.3953607708,"remaining_time":0.5240828822},
{"learn":[4.079840652],"iteration":430,"passed_time":0.3959420902,"remaining_time":0.5227170517},
{"learn":[4.075707828],"iteration":431,"passed_time":0.3964815133,"remaining_time":0.5212997675},
{"learn":[4.071345409],"iteration":432,"passed_time":0.3970079571,"remaining_time":0.519869542},
{"learn":[4.067460475],"iteration":433,"passed_time":0.3975633916,"remaining_time":0.5184812896},
{"learn":[4.064914749],"iteration":434,"passed_time":0.3981151213,"remaining_time":0.5170920541},
{"learn":[4.063823175],"iteration":435,"passed_time":0.3986258295,"remaining_time":0.5156535959},
{"learn":[4.058898471],"iteration":436,"passed_time":0.3991502965,"remaining_time":0.5142371097},
{"learn":[4.054120355],"iteration":437,"passed_time":0.3996849891,"remaining_time":0.5128378171},
{"learn":[4.052715901],"iteration":438,"passed_time":0.4001799082,"remaining_time":0.5113916367},
{"learn":[4.052114167],"iteration":439,"passed_time":0.4006638111,"remaining_time":0.5099357596},
{"learn":[4.051377267],"iteration":440,"passed_time":0.4011418926,"remaining_time":0.5084769114},
{"learn":[4.049275336],"iteration":441,"passed_time":0.4016232158,"remaining_time":0.5070265937},
{"learn":[4.047099198],"iteration":442,"passed_time":0.4021236363,"remaining_time":0.5056046624},
{"learn":[4.044348685],"iteration":443,"passed_time":0.4026450596,"remaining_time":0.5042131827},
{"learn":[4.042822379],"iteration":444,"passed_time":0.4031601851,"remaining_time":0.5028177589},
{"learn":[4.041258611],"iteration":445,"passed_time":0.4036479306,"remaining_time":0.5013922725},
{"learn":[4.040044254],"iteration":446,"passed_time":0.4041667709,"remaining_time":0.5000094504},
{"learn":[4.036860137],"iteration":447,"passed_time":0.40468708,"remaining_time":0.498632295},
{"learn":[4.036372284],"iteration":448,"passed_time":0.4052932928,"remaining_time":0.4973643749},
{"learn":[4.03368231],"iteration":449,"passed_time":0.4058729372,"remaining_time":0.4960669233},
{"learn":[4.032439519],"iteration":450,"passed_time":0.4064853293,"remaining_time":0.4948125184},
{"learn":[4.032008634],"iteration":451,"passed_time":0.4070294748,"remaining_time":0.4934782128},
{"learn":[4.030034932],"iteration":452,"passed_time":0.4075527653,"remaining_time":0.4921222133},
{"learn":[4.028173412],"iteration":453,"passed_time":0.4080637999,"remaining_time":0.4907551426},
{"learn":[4.023806097],"iteration":454,"passed_time":0.4085850597,"remaining_time":0.4894040825},
{"learn":[4.020239186],"iteration":455,"passed_time":0.4090886878,"remaining_time":0.4880356276},
{"learn":[4.017384838],"iteration":456,"passed_time":0.4096014541,"remaining_time":0.4866818153},
{"learn":[4.016468229],"iteration":457,"passed_time":0.4101090964,"remaining_time":0.4853256119},
{"learn":[4.014530169],"iteration":458,"passed_time":0.4106309987,"remaining_time":0.4839899135},
{"learn":[4.012884822],"iteration":459,"passed_time":0.41114508,"remaining_time":0.4826485722},
{"learn":[4.008924707],"iteration":460,"passed_time":0.4118461071,"remaining_time":0.4815293964},
{"learn":[4.008286778],"iteration":461,"passed_time":0.4123558828,"remaining_time":0.480189318},
{"learn":[4.006444202],"iteration":462,"passed_time":0.4128534864,"remaining_time":0.4788387088},
{"learn":[4.003284363],"iteration":463,"passed_time":0.413381547,"remaining_time":0.4775269594},
{"learn":[3.999811484],"iteration":464,"passed_time":0.4139147138,"remaining_time":0.4762244556},
{"learn":[3.997483319],"iteration":465,"passed_time":0.4144259321,"remaining_time":0.4749001025},
{"learn":[3.99708333],"iteration":466,"passed_time":0.4149295178,"remaining_time":0.4735705203},
{"learn":[3.995860263],"iteration":467,"passed_time":0.4154567996,"remaining_time":0.4722714046},
{"learn":[3.994131111],"iteration":468,"passed_time":0.4159572604,"remaining_time":0.4709452138},
{"learn":[3.993125499],"iteration":469,"passed_time":0.4164894015,"remaining_time":0.4696582613},
{"learn":[3.992954084],"iteration":470,"passed_time":0.4169920175,"remaining_time":0.468341353},
{"learn":[3.990635743],"iteration":471,"passed_time":0.4175191552,"remaining_time":0.4670553262},
{"learn":[3.986678254],"iteration":472,"passed_time":0.4180181791,"remaining_time":0.4657411847},
{"learn":[3.986393291],"iteration":473,"passed_time":0.4185130321,"remaining_time":0.4644258542},
{"learn":[3.986152671],"iteration":474,"passed_time":0.4189956504,"remaining_time":0.4631004557},
{"learn":[3.985596662],"iteration":475,"passed_time":0.4194841094,"remaining_time":0.461785028},
{"learn":[3.983853457],"iteration":476,"passed_time":0.4200060556,"remaining_time":0.4605097842},
{"learn":[3.983263928],"iteration":477,"passed_time":0.4206970958,"remaining_time":0.4594223515},
{"learn":[3.980067202],"iteration":478,"passed_time":0.4213641937,"remaining_time":0.4583105322},
{"learn":[3.978115407],"iteration":479,"passed_time":0.4218811329,"remaining_time":0.457037894},
{"learn":[3.972661644],"iteration":480,"passed_time":0.4223859875,"remaining_time":0.4557553587},
{"learn":[3.969938254],"iteration":481,"passed_time":0.4229026691,"remaining_time":0.4544887606},
{"learn":[3.968211434],"iteration":482,"passed_time":0.423406741,"remaining_time":0.4532117704},
{"learn":[3.966113368],"iteration":483,"passed_time":0.4239397566,"remaining_time":0.4519688314},
{"learn":[3.962246044],"iteration":484,"passed_time":0.4244678657,"remaining_time":0.4507236099},
{"learn":[3.961319703],"iteration":485,"passed_time":0.4249897067,"remaining_time":0.4494747103},
{"learn":[3.96078191],"iteration":486,"passed_time":0.425482305,"remaining_time":0.4481979928},
{"learn":[3.958913633],"iteration":487,"passed_time":0.4259838758,"remaining_time":0.4469339024},
{"learn":[3.957428286],"iteration":488,"passed_time":0.4264875324,"remaining_time":0.4456751105},
{"learn":[3.952641965],"iteration":489,"passed_time":0.4269834411,"remaining_time":0.4444113366},
{"learn":[3.951486786],"iteration":490,"passed_time":0.4274768896,"remaining_time":0.4431481401},
{"learn":[3.94938344],"iteration":491,"passed_time":0.4279818937,"remaining_time":0.441900004},
{"learn":[3.947297924],"iteration":492,"passed_time":0.4285108879,"remaining_time":0.4406795541},
{"learn":[3.946284886],"iteration":493,"passed_time":0.4290698589,"remaining_time":0.4394926085},
{"learn":[3.943288204],"iteration":494,"passed_time":0.4295932132,"remaining_time":0.438271864},
{"learn":[3.943076488],"iteration":495,"passed_time":0.430099395,"remaining_time":0.437036482},
{"learn":[3.942347078],"iteration":496,"passed_time":0.4305810468,"remaining_time":0.4357792083},
{"learn":[3.940251541],"iteration":497,"passed_time":0.4310514773,"remaining_time":0.4345137382},
{"learn":[3.939011019],"iteration":498,"passed_time":0.4315414004,"remaining_time":0.4332710253},
{"learn":[3.938760512],"iteration":499,"passed_time":0.432035819,"remaining_time":0.432035819},
{"learn":[3.934522727],"iteration":500,"passed_time":0.4325338546,"remaining_time":0.4308071726},
{"learn":[3.930091193],"iteration":501,"passed_time":0.4330725635,"remaining_time":0.4296217861},
{"learn":[3.927671752],"iteration":502,"passed_time":0.4335846955,"remaining_time":0.4284127111},
{"learn":[3.927280041],"iteration":503,"passed_time":0.434068191,"remaining_time":0.4271782197},
{"learn":[3.925987561],"iteration":504,"passed_time":0.4345499427,"remaining_time":0.4259449934},
{"learn":[3.921645957],"iteration":505,"passed_time":0.4350591847,"remaining_time":0.4247415755},
{"learn":[3.920333743],"iteration":506,"passed_time":0.4357562044,"remaining_time":0.4237234887},
{"learn":[3.918659461],"iteration":507,"passed_time":0.4363323184,"remaining_time":0.4225895682},
{"learn":[3.916124385],"iteration":508,"passed_time":0.4369501606,"remaining_time":0.4214980921},
{"learn":[3.913849268],"iteration":509,"passed_time":0.4374884671,"remaining_time":0.4203320567},
{"learn":[3.912826119],"iteration":510,"passed_time":0.4379919101,"remaining_time":0.4191351155},
{"learn":[3.910034145],"iteration":511,"passed_time":0.4384814051,"remaining_time":0.4179275892},
{"learn":[3.90792379],"iteration":512,"passed_time":0.4390338978,"remaining_time":0.4167826671},
{"learn":[3.907823851],"iteration":513,"passed_time":0.4395509005,"remaining_time":0.4156064935},
{"learn":[3.904527401],"iteration":514,"passed_time":0.4400478799,"remaining_time":0.4144140228},
{"learn":[3.903378283],"iteration":515,"passed_time":0.4405595074,"remaining_time":0.4132379876},
{"learn":[3.902170135],"iteration":516,"passed_time":0.4410656003,"remaining_time":0.4120593519},
{"learn":[3.899435429],"iteration":517,"passed_time":0.4415660105,"remaining_time":0.4108780252},
{"learn":[3.897497505],"iteration":518,"passed_time":0.4420663821,"remaining_time":0.4096992867},
{"learn":[3.896426119],"iteration":519,"passed_time":0.4425843752,"remaining_time":0.4085394232},
{"learn":[3.896044669],"iteration":520,"passed_time":0.4430708118,"remaining_time":0.4073530112},
{"learn":[3.892795942],"iteration":521,"passed_time":0.4435698738,"remaining_time":0.4061808423},
{"learn":[3.892413888],"iteration":522,"passed_time":0.4440705801,"remaining_time":0.405012747},
{"learn":[3.891738985],"iteration":523,"passed_time":0.4445667217,"remaining_time":0.4038430525},
{"learn":[3.88822057],"iteration":524,"passed_time":0.445076904,"remaining_time":0.4026886275},
{"learn":[3.883837053],"iteration":525,"passed_time":0.445598881,"remaining_time":0.4015472806},
{"learn":[3.881769742],"iteration":526,"passed_time":0.4461174509,"remaining_time":0.4004052263},
{"learn":[3.880356898],"iteration":527,"passed_time":0.4466239012,"remaining_time":0.3992546996},
{"learn":[3.879250273],"iteration":528,"passed_time":0.4471415511,"remaining_time":0.3981165795},
{"learn":[3.877174493],"iteration":529,"passed_time":0.4476173911,"remaining_time":0.3969437242},
{"learn":[3.875854201],"iteration":530,"passed_time":0.4481108421,"remaining_time":0.3957890489},
{"learn":[3.873189396],"iteration":531,"passed_time":0.4485966629,"remaining_time":0.3946301471},
{"learn":[3.871583368],"iteration":532,"passed_time":0.4491019877,"remaining_time":0.3934908598},
{"learn":[3.869622679],"iteration":533,"passed_time":0.4496230235,"remaining_time":0.3923676572},
{"learn":[3.866860164],"iteration":534,"passed_time":0.4501688265,"remaining_time":0.3912682323},
{"learn":[3.864498444],"iteration":535,"passed_time":0.4508134622,"remaining_time":0.3902564299},
{"learn":[3.861416322],"iteration":536,"passed_time":0.4514334984,"remaining_time":0.3892247854},
{"learn":[3.860265769],"iteration":537,"passed_time":0.4519216891,"remaining_time":0.3880814505},
{"learn":[3.859328725],"iteration":538,"passed_time":0.452501142,"remaining_time":0.3870186019},
{"learn":[3.858521278],"iteration":539,"passed_time":0.4530553978,"remaining_time":0.3859360796},
{"learn":[3.85599111],"iteration":540,"passed_time":0.4536224011,"remaining_time":0.3848663255},
{"learn":[3.852379816],"iteration":541,"passed_time":0.4542231831,"remaining_time":0.3838269702},
{"learn":[3.851327537],"iteration":542,"passed_time":0.454789856,"remaining_time":0.3827605234},
{"learn":[3.847854898],"iteration":543,"passed_time":0.4553898181,"remaining_time":0.3817238182},
{"learn":[3.847083414],"iteration":544,"passed_time":0.4559116916,"remaining_time":0.3806235223},
{"learn":[3.845397429],"iteration":545,"passed_time":0.456498161,"remaining_time":0.379579057},
{"learn":[3.841933528],"iteration":546,"passed_time":0.4570098364,"remaining_time":0.3784743252},
{"learn":[3.840996474],"iteration":547,"passed_time":0.457533103,"remaining_time":0.3773813185},
{"learn":[3.838355966],"iteration":548,"passed_time":0.458020562,"remaining_time":0.3762609717},
{"learn":[3.83342799],"iteration":549,"passed_time":0.4585309858,"remaining_time":0.3751617157},
{"learn":[3.828161535],"iteration":550,"passed_time":0.4590355586,"remaining_time":0.3740598291},
{"learn":[3.823502399],"iteration":551,"passed_time":0.4595625711,"remaining_time":0.3729783185},
{"learn":[3.820068862],"iteration":552,"passed_time":0.4601036577,"remaining_time":0.3719101899},
{"learn":[3.817951642],"iteration":553,"passed_time":0.4606246001,"remaining_time":0.3708277466},
{"learn":[3.815785958],"iteration":554,"passed_time":0.4611234691,"remaining_time":0.3697296284},
{"learn":[3.81503012],"iteration":555,"passed_time":0.4616443986,"remaining_time":0.3686512823},
{"learn":[3.813529315],"iteration":556,"passed_time":0.4621571413,"remaining_time":0.3675684266},
{"learn":[3.808881326],"iteration":557,"passed_time":0.4626720788,"remaining_time":0.3664893527},
{"learn":[3.808740434],"iteration":558,"passed_time":0.4631707634,"remaining_time":0.3653994752},
{"learn":[3.80714352],"iteration":559,"passed_time":0.4636636272,"remaining_time":0.3643071357},
{"learn":[3.80573346],"iteration":560,"passed_time":0.4641628558,"remaining_time":0.3632219139},
{"learn":[3.803370052],"iteration":561,"passed_time":0.4647222506,"remaining_time":0.3621856687},
{"learn":[3.803215211],"iteration":562,"passed_time":0.4653061408,"remaining_time":0.3611701306},
{"learn":[3.801309667],"iteration":563,"passed_time":0.4659028233,"remaining_time":0.3601660124},
{"learn":[3.800003847],"iteration":564,"passed_time":0.4666782432,"remaining_time":0.3593009483},
{"learn":[3.798026138],"iteration":565,"passed_time":0.4676795434,"remaining_time":0.3586094025},
{"learn":[3.794745847],"iteration":566,"passed_time":0.4687546324,"remaining_time":0.3579731143},
{"learn":[3.794312041],"iteration":567,"passed_time":0.4697246943,"remaining_time":0.3572554013},
{"learn":[3.792205926],"iteration":568,"passed_time":0.4705568763,"remaining_time":0.3564323615},
{"learn":[3.788991061],"iteration":569,"passed_time":0.47109451,"remaining_time":0.3553870865},
{"learn":[3.787391572],"iteration":570,"passed_time":0.4716142083,"remaining_time":0.3543301145},
{"learn":[3.7826445],"iteration":571,"passed_time":0.4721278333,"remaining_time":0.3532704767},
{"learn":[3.781700331],"iteration":572,"passed_time":0.4726406331,"remaining_time":0.3522121297},
{"learn":[3.780045374],"iteration":573,"passed_time":0.4731623764,"remaining_time":0.3511623211},
{"learn":[3.775462644],"iteration":574,"passed_time":0.473701096,"remaining_time":0.350126897},
{"learn":[3.773711943],"iteration":575,"passed_time":0.4742734359,"remaining_time":0.3491179459},
{"learn":[3.772415806],"iteration":576,"passed_time":0.4748475639,"remaining_time":0.3481118189},
{"learn":[3.770170875],"iteration":577,"passed_time":0.4753700734,"remaining_time":0.3470695},
{"learn":[3.765166479],"iteration":578,"passed_time":0.4759005072,"remaining_time":0.3460347384},
{"learn":[3.763976102],"iteration":579,"passed_time":0.476399318,"remaining_time":0.3449788165},
{"learn":[3.760761708],"iteration":580,"passed_time":0.4769192311,"remaining_time":0.3439400307},
{"learn":[3.758155662],"iteration":581,"passed_time":0.4774454409,"remaining_time":0.3429075503},
{"learn":[3.756844548],"iteration":582,"passed_time":0.4779721751,"remaining_time":0.3418771818},
{"learn":[3.753098923],"iteration":583,"passed_time":0.4784921938,"remaining_time":0.3408437545},
{"learn":[3.751618946],"iteration":584,"passed_time":0.4790719549,"remaining_time":0.3398544637},
{"learn":[3.751398464],"iteration":585,"passed_time":0.4796309373,"remaining_time":0.3388518909},
{"learn":[3.749920103],"iteration":586,"passed_time":0.4801335911,"remaining_time":0.3378111978},
{"learn":[3.748237465],"iteration":587,"passed_time":0.4806487533,"remaining_time":0.3367810993},
{"learn":[3.746021536],"iteration":588,"passed_time":0.4812083012,"remaining_time":0.3357837212},
{"learn":[3.74417648],"iteration":589,"passed_time":0.4818317826,"remaining_time":0.3348322557},
{"learn":[3.738788389],"iteration":590,"passed_time":0.4824543132,"remaining_time":0.3338812422},
{"learn":[3.736021611],"iteration":591,"passed_time":0.4830243429,"remaining_time":0.3328951552},
{"learn":[3.734546151],"iteration":592,"passed_time":0.4835343336,"remaining_time":0.3318692644},
{"learn":[3.733527479],"iteration":593,"passed_time":0.4840415057,"remaining_time":0.330843184},
{"learn":[3.733026392],"iteration":594,"passed_time":0.4845602815,"remaining_time":0.3298267462},
{"learn":[3.730314752],"iteration":595,"passed_time":0.4850788307,"remaining_time":0.3288118248},
{"learn":[3.727342596],"iteration":596,"passed_time":0.4855968138,"remaining_time":0.3277981842},
{"learn":[3.725459604],"iteration":597,"passed_time":0.4860903814,"remaining_time":0.3267697882},
{"learn":[3.723158842],"iteration":598,"passed_time":0.4865842017,"remaining_time":0.3257433471},
{"learn":[3.722362756],"iteration":599,"passed_time":0.4870981645,"remaining_time":0.3247321097},
{"learn":[3.721443615],"iteration":600,"passed_time":0.4876039353,"remaining_time":0.3237170885},
{"learn":[3.720743486],"iteration":601,"passed_time":0.488119988,"remaining_time":0.3227105568},
{"learn":[3.720215334],"iteration":602,"passed_time":0.4886079593,"remaining_time":0.3216871639},
{"learn":[3.719436563],"iteration":603,"passed_time":0.4890975685,"remaining_time":0.3206666177},
{"learn":[3.715046574],"iteration":604,"passed_time":0.4896093754,"remaining_time":0.3196623195},
{"learn":[3.71443396],"iteration":605,"passed_time":0.4900876813,"remaining_time":0.3186378654},
{"learn":[3.712938941],"iteration":606,"passed_time":0.4905664566,"remaining_time":0.3176155147},
{"learn":[3.712814764],"iteration":607,"passed_time":0.4910765551,"remaining_time":0.3166151474},
{"learn":[3.71235348],"iteration":608,"passed_time":0.4915656637,"remaining_time":0.3156029138},
{"learn":[3.711223749],"iteration":609,"passed_time":0.4920774361,"remaining_time":0.3146068854},
{"learn":[3.710755648],"iteration":610,"passed_time":0.4925930611,"remaining_time":0.3136148949},
{"learn":[3.708668039],"iteration":611,"passed_time":0.4931144333,"remaining_time":0.3126281048},
{"learn":[3.705623591],"iteration":612,"passed_time":0.4936204373,"remaining_time":0.3116331309},
{"learn":[3.704045802],"iteration":613,"passed_time":0.4941515956,"remaining_time":0.3106555634},
{"learn":[3.699915209],"iteration":614,"passed_time":0.494670757,"remaining_time":0.3096719373},
{"learn":[3.696182221],"iteration":615,"passed_time":0.4951913101,"remaining_time":0.3086906868},
{"learn":[3.694263278],"iteration":616,"passed_time":0.4956993388,"remaining_time":0.3077031552},
{"learn":[3.693810229],"iteration":617,"passed_time":0.4961808343,"remaining_time":0.3067007746},
{"learn":[3.690900932],"iteration":618,"passed_time":0.4967540194,"remaining_time":0.3057565128},
{"learn":[3.688020895],"iteration":619,"passed_time":0.4974042704,"remaining_time":0.3048606819},
{"learn":[3.685491894],"iteration":620,"passed_time":0.4980005295,"remaining_time":0.3039326903},
{"learn":[3.684328128],"iteration":621,"passed_time":0.4985182225,"remaining_time":0.3029580195},
{"learn":[3.680640153],"iteration":622,"passed_time":0.4990481814,"remaining_time":0.3019922382},
{"learn":[3.678932783],"iteration":623,"passed_time":0.4995704544,"remaining_time":0.3010232225},
{"learn":[3.674167041],"iteration":624,"passed_time":0.500054104,"remaining_time":0.3000324624},
{"learn":[3.672200976],"iteration":625,"passed_time":0.5005712823,"remaining_time":0.2990633539},
{"learn":[3.670606604],"iteration":626,"passed_time":0.5010706147,"remaining_time":0.2980850706},
{"learn":[3.665506042],"iteration":627,"passed_time":0.5015541302,"remaining_time":0.2970989434},
{"learn":[3.664214007],"iteration":628,"passed_time":0.5020702482,"remaining_time":0.296133644},
{"learn":[3.66261643],"iteration":629,"passed_time":0.5025962624,"remaining_time":0.2951755827},
{"learn":[3.662118449],"iteration":630,"passed_time":0.5030833665,"remaining_time":0.2941961367},
{"learn":[3.660871366],"iteration":631,"passed_time":0.503580765,"remaining_time":0.2932242429},
{"learn":[3.656695243],"iteration":632,"passed_time":0.5040890918,"remaining_time":0.2922601844},
{"learn":[3.654497801],"iteration":633,"passed_time":0.5046226246,"remaining_time":0.2913121145},
{"learn":[3.654189134],"iteration":634,"passed_time":0.5051313796,"remaining_time":0.290351108},
{"learn":[3.653957699],"iteration":635,"passed_time":0.5058262449,"remaining_time":0.2894980395},
{"learn":[3.651920725],"iteration":636,"passed_time":0.5063739529,"remaining_time":0.288561609},
{"learn":[3.65106705],"iteration":637,"passed_time":0.5069410315,"remaining_time":0.2876373878},
{"learn":[3.650612844],"iteration":638,"passed_time":0.5074578134,"remaining_time":0.2866858695},
{"learn":[3.649884732],"iteration":639,"passed_time":0.5079733288,"remaining_time":0.2857349974},
{"learn":[3.646276182],"iteration":640,"passed_time":0.5084945801,"remaining_time":0.2847886962},
{"learn":[3.645808194],"iteration":641,"passed_time":0.5089852003,"remaining_time":0.2838266382},
{"learn":[3.645042989],"iteration":642,"passed_time":0.5094999141,"remaining_time":0.2828794235},
{"learn":[3.639864499],"iteration":643,"passed_time":0.5100154213,"remaining_time":0.2819339906},
{"learn":[3.637318478],"iteration":644,"passed_time":0.5105293741,"remaining_time":0.2809890354},
{"learn":[3.636344905],"iteration":645,"passed_time":0.5110433056,"remaining_time":0.2800454027},
{"learn":[3.634754643],"iteration":646,"passed_time":0.5115163322,"remaining_time":0.2790807809},
{"learn":[3.630724975],"iteration":647,"passed_time":0.5122058373,"remaining_time":0.2782352696},
{"learn":[3.629408252],"iteration":648,"passed_time":0.5128689716,"remaining_time":0.277375977},
{"learn":[3.62790646],"iteration":649,"passed_time":0.5134374747,"remaining_time":0.2764663325},
{"learn":[3.627388973],"iteration":650,"passed_time":0.5139369652,"remaining_time":0.2755207386},
{"learn":[3.625163557],"iteration":651,"passed_time":0.5144529551,"remaining_time":0.2745853196},
{"learn":[3.623701985],"iteration":652,"passed_time":0.5149491271,"remaining_time":0.273640654},
{"learn":[3.622342639],"iteration":653,"passed_time":0.5154714272,"remaining_time":0.2727111832},
{"learn":[3.621130639],"iteration":654,"passed_time":0.5159704928,"remaining_time":0.2717707176},
{"learn":[3.619125665],"iteration":655,"passed_time":0.516480079,"remaining_time":0.2708371146},
{"learn":[3.618878783],"iteration":656,"passed_time":0.5169448518,"remaining_time":0.2698814066},
{"learn":[3.616207429],"iteration":657,"passed_time":0.517471743,"remaining_time":0.2689594773},
{"learn":[3.61206486],"iteration":658,"passed_time":0.5180104084,"remaining_time":0.2680448395},
{"learn":[3.611955873],"iteration":659,"passed_time":0.5184922753,"remaining_time":0.2671020812},
{"learn":[3.610713743],"iteration":660,"passed_time":0.5190041982,"remaining_time":0.2661761319},
{"learn":[3.610044025],"iteration":661,"passed_time":0.5195135294,"remaining_time":0.2652501102},
{"learn":[3.607342669],"iteration":662,"passed_time":0.5200221513,"remaining_time":0.2643249849},
{"learn":[3.602510618],"iteration":663,"passed_time":0.5205346471,"remaining_time":0.2634030745},
{"learn":[3.600492392],"iteration":664,"passed_time":0.5212325302,"remaining_time":0.2625757859},
{"learn":[3.597171065],"iteration":665,"passed_time":0.5218634306,"remaining_time":0.261715294},
{"learn":[3.594358798],"iteration":666,"passed_time":0.5224156283,"remaining_time":0.2608161982},
{"learn":[3.593945251],"iteration":667,"passed_time":0.522943797,"remaining_time":0.2599061985},
{"learn":[3.593607748],"iteration":668,"passed_time":0.5234310637,"remaining_time":0.2589771033},
{"learn":[3.592238714],"iteration":669,"passed_time":0.5239496611,"remaining_time":0.2580647585},
{"learn":[3.590144654],"iteration":670,"passed_time":0.5244478384,"remaining_time":0.257143575},
{"learn":[3.587151536],"iteration":671,"passed_time":0.5249507591,"remaining_time":0.2562259657},
{"learn":[3.586070865],"iteration":672,"passed_time":0.5254818424,"remaining_time":0.2553232726},
{"learn":[3.585102746],"iteration":673,"passed_time":0.5260151023,"remaining_time":0.254422735},
{"learn":[3.584362847],"iteration":674,"passed_time":0.5264804381,"remaining_time":0.2534905813},
{"learn":[3.581407561],"iteration":675,"passed_time":0.5270197068,"remaining_time":0.2525952441},
{"learn":[3.57919422],"iteration":676,"passed_time":0.5276510017,"remaining_time":0.2517448649},
{"learn":[3.577632204],"iteration":677,"passed_time":0.5282338255,"remaining_time":0.2508721118},
{"learn":[3.573911195],"iteration":678,"passed_time":0.5288196532,"remaining_time":0.2500016328},
{"learn":[3.573408216],"iteration":679,"passed_time":0.5293382035,"remaining_time":0.2491003311},
{"learn":[3.571076482],"iteration":680,"passed_time":0.5298602065,"remaining_time":0.2482017707},
{"learn":[3.568177107],"iteration":681,"passed_time":0.5303679993,"remaining_time":0.2472976888},
{"learn":[3.564824621],"iteration":682,"passed_time":0.5308671886,"remaining_time":0.2463907742},
{"learn":[3.562475026],"iteration":683,"passed_time":0.5313574382,"remaining_time":0.2454809217},
{"learn":[3.561226889],"iteration":684,"passed_time":0.5318682188,"remaining_time":0.2445817356},
{"learn":[3.559383467],"iteration":685,"passed_time":0.5323881544,"remaining_time":0.2436878724},
{"learn":[3.555209766],"iteration":686,"passed_time":0.5328665911,"remaining_time":0.2427761907},
{"learn":[3.55345383],"iteration":687,"passed_time":0.5333736144,"remaining_time":0.2418787321},
{"learn":[3.552300968],"iteration":688,"passed_time":0.5338671736,"remaining_time":0.2409763294},
{"learn":[3.551253986],"iteration":689,"passed_time":0.5343656965,"remaining_time":0.2400773419},
{"learn":[3.549807725],"iteration":690,"passed_time":0.5348537902,"remaining_time":0.2391748497},
{"learn":[3.547992926],"iteration":691,"passed_time":0.5353528833,"remaining_time":0.2382784509},
{"learn":[3.545438607],"iteration":692,"passed_time":0.535934045,"remaining_time":0.2374195553},
{"learn":[3.543313763],"iteration":693,"passed_time":0.5365069846,"remaining_time":0.2365578347},
{"learn":[3.542962896],"iteration":694,"passed_time":0.5370026089,"remaining_time":0.2356630154},
{"learn":[3.539800465],"iteration":695,"passed_time":0.5375268662,"remaining_time":0.2347818496},
{"learn":[3.53953187],"iteration":696,"passed_time":0.5380080214,"remaining_time":0.2338829706},
{"learn":[3.536332425],"iteration":697,"passed_time":0.5385165174,"remaining_time":0.2329971178},
{"learn":[3.534993327],"iteration":698,"passed_time":0.5390135613,"remaining_time":0.2321074134},
{"learn":[3.531637011],"iteration":699,"passed_time":0.5395264046,"remaining_time":0.231225602},
{"learn":[3.531040284],"iteration":700,"passed_time":0.540024579,"remaining_time":0.2303385865},
{"learn":[3.529973872],"iteration":701,"passed_time":0.5405113214,"remaining_time":0.2294478259},
{"learn":[3.527325183],"iteration":702,"passed_time":0.5410526488,"remaining_time":0.2285812755},
{"learn":[3.527200815],"iteration":703,"passed_time":0.5415150132,"remaining_time":0.2276824487},
{"learn":[3.523459911],"iteration":704,"passed_time":0.5420030259,"remaining_time":0.2267955924},
{"learn":[3.522729934],"iteration":705,"passed_time":0.5425796804,"remaining_time":0.2259467791},
{"learn":[3.522260582],"iteration":706,"passed_time":0.5432764693,"remaining_time":0.2251485226},
{"learn":[3.518641591],"iteration":707,"passed_time":0.5438415494,"remaining_time":0.2242962322},
{"learn":[3.516856405],"iteration":708,"passed_time":0.5444001301,"remaining_time":0.2234420844},
{"learn":[3.515083413],"iteration":709,"passed_time":0.544913607,"remaining_time":0.2225703465},
{"learn":[3.514671214],"iteration":710,"passed_time":0.5454271931,"remaining_time":0.2216996608},
{"learn":[3.512617621],"iteration":711,"passed_time":0.5459026225,"remaining_time":0.2208145439},
{"learn":[3.510747971],"iteration":712,"passed_time":0.5464203305,"remaining_time":0.2199475945},
{"learn":[3.508149266],"iteration":713,"passed_time":0.5469395101,"remaining_time":0.2190822127},
{"learn":[3.504557165],"iteration":714,"passed_time":0.5474504898,"remaining_time":0.2182145309},
{"learn":[3.501367208],"iteration":715,"passed_time":0.5479465758,"remaining_time":0.2173419379},
{"learn":[3.497593362],"iteration":716,"passed_time":0.5484467148,"remaining_time":0.2164719948},
{"learn":[3.496291169],"iteration":717,"passed_time":0.5489432899,"remaining_time":0.2156016821},
{"learn":[3.49330374],"iteration":718,"passed_time":0.5494682996,"remaining_time":0.2147435218},
{"learn":[3.490044385],"iteration":719,"passed_time":0.5499612822,"remaining_time":0.213873832},
{"learn":[3.488891789],"iteration":720,"passed_time":0.5505423972,"remaining_time":0.213039291},
{"learn":[3.486869081],"iteration":721,"passed_time":0.5510999009,"remaining_time":0.2121963607},
{"learn":[3.486303638],"iteration":722,"passed_time":0.5515889025,"remaining_time":0.2113279751},
{"learn":[3.486035862],"iteration":723,"passed_time":0.5520807656,"remaining_time":0.2104617283},
{"learn":[3.482668951],"iteration":724,"passed_time":0.5526032491,"remaining_time":0.209608129},
{"learn":[3.47820549],"iteration":725,"passed_time":0.5530879565,"remaining_time":0.2087411847},
{"learn":[3.474392283],"iteration":726,"passed_time":0.5536019982,"remaining_time":0.2078863074},
{"learn":[3.472268163],"iteration":727,"passed_time":0.5541111313,"remaining_time":0.2070305326},
{"learn":[3.471209164],"iteration":728,"passed_time":0.5545965996,"remaining_time":0.2061669115},
{"learn":[3.470049971],"iteration":729,"passed_time":0.5550980829,"remaining_time":0.2053102499},
{"learn":[3.469078654],"iteration":730,"passed_time":0.555639663,"remaining_time":0.2044693151},
{"learn":[3.468643292],"iteration":731,"passed_time":0.55615541,"remaining_time":0.2036197403},
{"learn":[3.468134848],"iteration":732,"passed_time":0.556664019,"remaining_time":0.2027684762},
{"learn":[3.467820182],"iteration":733,"passed_time":0.5571656614,"remaining_time":0.2019156212},
{"learn":[3.465776156],"iteration":734,"passed_time":0.5578216715,"remaining_time":0.2011193781},
{"learn":[3.463037608],"iteration":735,"passed_time":0.5584292389,"remaining_time":0.20030614},
{"learn":[3.45965637],"iteration":736,"passed_time":0.5590487528,"remaining_time":0.1994977232},
{"learn":[3.457275091],"iteration":737,"passed_time":0.5596371305,"remaining_time":0.1986787645},
{"learn":[3.455522955],"iteration":738,"passed_time":0.5602360734,"remaining_time":0.1978641613},
{"learn":[3.451270508],"iteration":739,"passed_time":0.560763458,"remaining_time":0.1970249988},
{"learn":[3.450978947],"iteration":740,"passed_time":0.5613128103,"remaining_time":0.1961943561},
{"learn":[3.450608492],"iteration":741,"passed_time":0.5618743909,"remaining_time":0.1953687235},
{"learn":[3.448122004],"iteration":742,"passed_time":0.5624247685,"remaining_time":0.1945399266},
{"learn":[3.445646714],"iteration":743,"passed_time":0.5630007298,"remaining_time":0.1937206812},
{"learn":[3.44411263],"iteration":744,"passed_time":0.563535736,"remaining_time":0.1928880707},
{"learn":[3.443264164],"iteration":745,"passed_time":0.5640550983,"remaining_time":0.1920509316},
{"learn":[3.439521363],"iteration":746,"passed_time":0.5645562951,"remaining_time":0.1912084908},
{"learn":[3.436809225],"iteration":747,"passed_time":0.5650935977,"remaining_time":0.1903791265},
{"learn":[3.435509465],"iteration":748,"passed_time":0.5656688056,"remaining_time":0.1895632446},
{"learn":[3.434450277],"iteration":749,"passed_time":0.566199087,"remaining_time":0.188733029},
{"learn":[3.431786753],"iteration":750,"passed_time":0.5667392165,"remaining_time":0.1879068774},
{"learn":[3.430150302],"iteration":751,"passed_time":0.5672255863,"remaining_time":0.1870637572},
{"learn":[3.42696281],"iteration":752,"passed_time":0.5677634951,"remaining_time":0.1862384904},
{"learn":[3.426870334],"iteration":753,"passed_time":0.5682734808,"remaining_time":0.1854048757},
{"learn":[3.425200309],"iteration":754,"passed_time":0.5687759199,"remaining_time":0.1845696694},
{"learn":[3.423383783],"iteration":755,"passed_time":0.5692691511,"remaining_time":0.1837323715},
{"learn":[3.422752979],"iteration":756,"passed_time":0.5697649168,"remaining_time":0.1828967963},
{"learn":[3.420845924],"iteration":757,"passed_time":0.5702677711,"remaining_time":0.1820643807},
{"learn":[3.418917862],"iteration":758,"passed_time":0.5707630069,"remaining_time":0.1812304146},
{"learn":[3.417095735],"iteration":759,"passed_time":0.571270779,"remaining_time":0.1804012986},
{"learn":[3.414391848],"iteration":760,"passed_time":0.5717752705,"remaining_time":0.1795719969},
{"learn":[3.41426711],"iteration":761,"passed_time":0.5722612657,"remaining_time":0.1787377707},
{"learn":[3.411976013],"iteration":762,"passed_time":0.5727690043,"remaining_time":0.177911211},
{"learn":[3.408614844],"iteration":763,"passed_time":0.5733663144,"remaining_time":0.1771131547},
{"learn":[3.407906721],"iteration":764,"passed_time":0.5739859018,"remaining_time":0.1763224666},
{"learn":[3.407494015],"iteration":765,"passed_time":0.5746036417,"remaining_time":0.1755316608},
{"learn":[3.406287128],"iteration":766,"passed_time":0.5750929016,"remaining_time":0.1747022765},
{"learn":[3.404600442],"iteration":767,"passed_time":0.575593148,"remaining_time":0.1738770968},
{"learn":[3.404012662],"iteration":768,"passed_time":0.5760971856,"remaining_time":0.173053901},
{"learn":[3.400398762],"iteration":769,"passed_time":0.576625486,"remaining_time":0.1722387815},
{"learn":[3.399737714],"iteration":770,"passed_time":0.5771238609,"remaining_time":0.1714155177},
{"learn":[3.399185251],"iteration":771,"passed_time":0.5776257327,"remaining_time":0.1705941283},
{"learn":[3.397245411],"iteration":772,"passed_time":0.5781381337,"remaining_time":0.1697766576},
{"learn":[3.396229831],"iteration":773,"passed_time":0.5786436012,"remaining_time":0.1689579507},
{"learn":[3.394002836],"iteration":774,"passed_time":0.5792042653,"remaining_time":0.168156077},
{"learn":[3.389617243],"iteration":775,"passed_time":0.5797116047,"remaining_time":0.1673394323},
{"learn":[3.385426488],"iteration":776,"passed_time":0.5802056447,"remaining_time":0.1665197668},
{"learn":[3.385072258],"iteration":777,"passed_time":0.5807075233,"remaining_time":0.165703175},
{"learn":[3.383842366],"iteration":778,"passed_time":0.5811910342,"remaining_time":0.1648821804},
{"learn":[3.380110746],"iteration":779,"passed_time":0.5817195528,"remaining_time":0.1640747457},
{"learn":[3.378595218],"iteration":780,"passed_time":0.5822291868,"remaining_time":0.1632627297},
{"learn":[3.377371219],"iteration":781,"passed_time":0.5827444475,"remaining_time":0.1624530557},
{"learn":[3.375814782],"iteration":782,"passed_time":0.5832474984,"remaining_time":0.1616407499},
{"learn":[3.374195887],"iteration":783,"passed_time":0.5837527419,"remaining_time":0.160829837},
{"learn":[3.373704309],"iteration":784,"passed_time":0.5842523319,"remaining_time":0.1600181546},
{"learn":[3.372971757],"iteration":785,"passed_time":0.584781279,"remaining_time":0.1592152592},
{"learn":[3.371565136],"iteration":786,"passed_time":0.5852911281,"remaining_time":0.1584078911},
{"learn":[3.3700309],"iteration":787,"passed_time":0.5858064969,"remaining_time":0.1576027631},
{"learn":[3.368186663],"iteration":788,"passed_time":0.5862969113,"remaining_time":0.1567916962},
{"learn":[3.366710398],"iteration":789,"passed_time":0.5868150453,"remaining_time":0.1559888095},
{"learn":[3.364598042],"iteration":790,"passed_time":0.5873084153,"remaining_time":0.1551800996},
{"learn":[3.36348442],"iteration":791,"passed_time":0.5878002888,"remaining_time":0.154371793},
{"learn":[3.362001759],"iteration":792,"passed_time":0.5883344149,"remaining_time":0.1535753138},
{"learn":[3.361580401],"iteration":793,"passed_time":0.5889621519,"remaining_time":0.1528037825},
{"learn":[3.359543675],"iteration":794,"passed_time":0.5895850422,"remaining_time":0.1520313631},
{"learn":[3.35766119],"iteration":795,"passed_time":0.5901845356,"remaining_time":0.1512533232},
{"learn":[3.354592969],"iteration":796,"passed_time":0.5906914483,"remaining_time":0.1504521506},
{"learn":[3.350985986],"iteration":797,"passed_time":0.5912088063,"remaining_time":0.1496543595},
{"learn":[3.349589624],"iteration":798,"passed_time":0.5917252122,"remaining_time":0.1488570309},
{"learn":[3.349110856],"iteration":799,"passed_time":0.5922378144,"remaining_time":0.1480594536},
{"learn":[3.345315441],"iteration":800,"passed_time":0.5927544728,"remaining_time":0.1472635956},
{"learn":[3.34397474],"iteration":801,"passed_time":0.5933251496,"remaining_time":0.1464817701},
{"learn":[3.343800902],"iteration":802,"passed_time":0.5939359424,"remaining_time":0.1457103121},
{"learn":[3.342329465],"iteration":803,"passed_time":0.5945050616,"remaining_time":0.1449290946},
{"learn":[3.34220347],"iteration":804,"passed_time":0.5950050654,"remaining_time":0.1441316618},
{"learn":[3.341279219],"iteration":805,"passed_time":0.5955565111,"remaining_time":0.1433473488},
{"learn":[3.337329521],"iteration":806,"passed_time":0.5960759162,"remaining_time":0.1425559502},
{"learn":[3.336708453],"iteration":807,"passed_time":0.5965759846,"remaining_time":0.14176063},
{"learn":[3.333252703],"iteration":808,"passed_time":0.5970970907,"remaining_time":0.1409710066},
{"learn":[3.332186769],"iteration":809,"passed_time":0.5976094981,"remaining_time":0.1401800057},
{"learn":[3.330594851],"iteration":810,"passed_time":0.5981267555,"remaining_time":0.1393908222},
{"learn":[3.327867442],"iteration":811,"passed_time":0.5986724892,"remaining_time":0.1386089015},
{"learn":[3.327563111],"iteration":812,"passed_time":0.5991969302,"remaining_time":0.1378226642},
{"learn":[3.326308994],"iteration":813,"passed_time":0.5997008209,"remaining_time":0.1370323743},
{"learn":[3.326249879],"iteration":814,"passed_time":0.6003602928,"remaining_time":0.1362781033},
{"learn":[3.322336238],"iteration":815,"passed_time":0.6008961813,"remaining_time":0.1354961977},
{"learn":[3.320491154],"iteration":816,"passed_time":0.6014190747,"remaining_time":0.1347119837},
{"learn":[3.320434271],"iteration":817,"passed_time":0.6019291472,"remaining_time":0.133925556},
{"learn":[3.319609638],"iteration":818,"passed_time":0.6024393224,"remaining_time":0.1331398258},
{"learn":[3.316182682],"iteration":819,"passed_time":0.6029568088,"remaining_time":0.1323563727},
{"learn":[3.313126612],"iteration":820,"passed_time":0.6034417681,"remaining_time":0.1315664756},
{"learn":[3.311222803],"iteration":821,"passed_time":0.6040175963,"remaining_time":0.1307969977},
{"learn":[3.309627335],"iteration":822,"passed_time":0.6047151155,"remaining_time":0.1300541621},
{"learn":[3.307974895],"iteration":823,"passed_time":0.6053390596,"remaining_time":0.1292957215},
{"learn":[3.307321505],"iteration":824,"passed_time":0.6058825847,"remaining_time":0.1285205483},
{"learn":[3.306759087],"iteration":825,"passed_time":0.6063910247,"remaining_time":0.1277385451},
{"learn":[3.30484037],"iteration":826,"passed_time":0.6069028063,"remaining_time":0.1269579027},
{"learn":[3.30201994],"iteration":827,"passed_time":0.607440872,"remaining_time":0.1261833695},
{"learn":[3.299302297],"iteration":828,"passed_time":0.6086449482,"remaining_time":0.1255467867},
{"learn":[3.298132671],"iteration":829,"passed_time":0.6091552847,"remaining_time":0.1247667451},
{"learn":[3.296976183],"iteration":830,"passed_time":0.6096482027,"remaining_time":0.1239838102},
{"learn":[3.293144745],"iteration":831,"passed_time":0.610158141,"remaining_time":0.1232050092},
{"learn":[3.290284404],"iteration":832,"passed_time":0.6106600374,"remaining_time":0.1224252416},
{"learn":[3.288285745],"iteration":833,"passed_time":0.6111500597,"remaining_time":0.1216437769},
{"learn":[3.286662667],"iteration":834,"passed_time":0.6116930532,"remaining_time":0.1208734776},
{"learn":[3.285692682],"iteration":835,"passed_time":0.6122079847,"remaining_time":0.1200982171},
{"learn":[3.284565611],"iteration":836,"passed_time":0.6127331795,"remaining_time":0.1193255774},
{"learn":[3.283897383],"iteration":837,"passed_time":0.613224637,"remaining_time":0.1185470062},
{"learn":[3.280712855],"iteration":838,"passed_time":0.6137203769,"remaining_time":0.1177699412},
{"learn":[3.280468341],"iteration":839,"passed_time":0.614209624,"remaining_time":0.1169923093},
{"learn":[3.277814895],"iteration":840,"passed_time":0.6147104787,"remaining_time":0.1162175578},
{"learn":[3.276316385],"iteration":841,"passed_time":0.6152120583,"remaining_time":0.1154435929},
{"learn":[3.27557063],"iteration":842,"passed_time":0.6157094197,"remaining_time":0.1146694886},
{"learn":[3.27499628],"iteration":843,"passed_time":0.6162118776,"remaining_time":0.1138969821},
{"learn":[3.273569958],"iteration":844,"passed_time":0.6167178143,"remaining_time":0.1131257529},
{"learn":[3.269665595],"iteration":845,"passed_time":0.6172211502,"remaining_time":0.1123546775},
{"learn":[3.267984685],"iteration":846,"passed_time":0.6177544693,"remaining_time":0.1115896503},
{"learn":[3.267702508],"iteration":847,"passed_time":0.6182392099,"remaining_time":0.1108164621},
{"learn":[3.266671924],"iteration":848,"passed_time":0.6187429746,"remaining_time":0.1100473371},
{"learn":[3.265359825],"iteration":849,"passed_time":0.6193068128,"remaining_time":0.1092894375},
{"learn":[3.2618983],"iteration":850,"passed_time":0.6200104831,"remaining_time":0.1085564771},
{"learn":[3.260456253],"iteration":851,"passed_time":0.6206487975,"remaining_time":0.1078122324},
{"learn":[3.258389147],"iteration":852,"passed_time":0.621173449,"remaining_time":0.1070486483},
{"learn":[3.258108469],"iteration":853,"passed_time":0.6216745894,"remaining_time":0.1062816043},
{"learn":[3.256424936],"iteration":854,"passed_time":0.6222103605,"remaining_time":0.1055210553},
{"learn":[3.254817983],"iteration":855,"passed_time":0.6227684635,"remaining_time":0.1047647883},
{"learn":[3.253898449],"iteration":856,"passed_time":0.6232827585,"remaining_time":0.1040016738},
{"learn":[3.253023652],"iteration":857,"passed_time":0.6238167226,"remaining_time":0.1032423947},
{"learn":[3.252845542],"iteration":858,"passed_time":0.6243224556,"remaining_time":0.1024790061},
{"learn":[3.252316026],"iteration":859,"passed_time":0.6248279145,"remaining_time":0.1017161721},
{"learn":[3.24975301],"iteration":860,"passed_time":0.6253446054,"remaining_time":0.1009557493},
{"learn":[3.249151075],"iteration":861,"passed_time":0.6258324069,"remaining_time":0.100191267},
{"learn":[3.246257135],"iteration":862,"passed_time":0.6263406071,"remaining_time":0.09943066417},
{"learn":[3.243826471],"iteration":863,"passed_time":0.6268728731,"remaining_time":0.09867443373},
{"learn":[3.243190653],"iteration":864,"passed_time":0.6273874813,"remaining_time":0.09791596529},
{"learn":[3.24008797],"iteration":865,"passed_time":0.6278918422,"remaining_time":0.09715647443},
{"learn":[3.240036811],"iteration":866,"passed_time":0.6283892557,"remaining_time":0.09639650635},
{"learn":[3.238676314],"iteration":867,"passed_time":0.6288826179,"remaining_time":0.09563652714},
{"learn":[3.237848782],"iteration":868,"passed_time":0.6293993391,"remaining_time":0.09488068288},
{"learn":[3.236405498],"iteration":869,"passed_time":0.6298757445,"remaining_time":0.09411936412},
{"learn":[3.233378068],"iteration":870,"passed_time":0.6303962955,"remaining_time":0.09336523779},
{"learn":[3.233169169],"iteration":871,"passed_time":0.6308640654,"remaining_time":0.0926038995},
{"learn":[3.232434885],"iteration":872,"passed_time":0.6313403977,"remaining_time":0.09184447938},
{"learn":[3.229978115],"iteration":873,"passed_time":0.6318637691,"remaining_time":0.09109248845},
{"learn":[3.229648848],"iteration":874,"passed_time":0.6323577478,"remaining_time":0.09033682111},
{"learn":[3.227208761],"iteration":875,"passed_time":0.6328762164,"remaining_time":0.08958521784},
{"learn":[3.226258869],"iteration":876,"passed_time":0.6333817167,"remaining_time":0.08883232743},
{"learn":[3.225331995],"iteration":877,"passed_time":0.6339039526,"remaining_time":0.08808232599},
{"learn":[3.221968268],"iteration":878,"passed_time":0.6343912076,"remaining_time":0.08732802744},
{"learn":[3.221166317],"iteration":879,"passed_time":0.6350236545,"remaining_time":0.0865941347},
{"learn":[3.220047503],"iteration":880,"passed_time":0.6357266769,"remaining_time":0.08587000517},
{"learn":[3.21982781],"iteration":881,"passed_time":0.6363003918,"remaining_time":0.08512862385},
{"learn":[3.216693405],"iteration":882,"passed_time":0.6368719672,"remaining_time":0.0843873388},
{"learn":[3.214798761],"iteration":883,"passed_time":0.6374523087,"remaining_time":0.08364758802},
{"learn":[3.214395085],"iteration":884,"passed_time":0.6379632146,"remaining_time":0.08289917477},
{"learn":[3.213470696],"iteration":885,"passed_time":0.6384707377,"remaining_time":0.08215086241},
{"learn":[3.211595017],"iteration":886,"passed_time":0.6389973691,"remaining_time":0.08140552729},
{"learn":[3.210965255],"iteration":887,"passed_time":0.6395284307,"remaining_time":0.08066124351},
{"learn":[3.209413583],"iteration":888,"passed_time":0.6400290871,"remaining_time":0.07991364304},
{"learn":[3.208331683],"iteration":889,"passed_time":0.6405455942,"remaining_time":0.07916855659},
{"learn":[3.207110711],"iteration":890,"passed_time":0.6410704851,"remaining_time":0.07842500884},
{"learn":[3.204519413],"iteration":891,"passed_time":0.6415724768,"remaining_time":0.0776791788},
{"learn":[3.201421296],"iteration":892,"passed_time":0.6420905355,"remaining_time":0.07693582004},
{"learn":[3.200691259],"iteration":893,"passed_time":0.6425996486,"remaining_time":0.07619190465},
{"learn":[3.200485067],"iteration":894,"passed_time":0.643101087,"remaining_time":0.07544761355},
{"learn":[3.197467568],"iteration":895,"passed_time":0.6436318268,"remaining_time":0.07470726561},
{"learn":[3.195838544],"iteration":896,"passed_time":0.6441623732,"remaining_time":0.07396736281},
{"learn":[3.195671746],"iteration":897,"passed_time":0.6446563672,"remaining_time":0.07322377445},
{"learn":[3.194213094],"iteration":898,"passed_time":0.645140461,"remaining_time":0.0724796291},
{"learn":[3.192884691],"iteration":899,"passed_time":0.645644773,"remaining_time":0.07173830811},
{"learn":[3.188364239],"iteration":900,"passed_time":0.646152935,"remaining_time":0.07099793626},
{"learn":[3.185219478],"iteration":901,"passed_time":0.6466697733,"remaining_time":0.07025902193},
{"learn":[3.184120387],"iteration":902,"passed_time":0.6471828385,"remaining_time":0.06952019417},
{"learn":[3.183725321],"iteration":903,"passed_time":0.6476918258,"remaining_time":0.06878143282},
{"learn":[3.181264554],"iteration":904,"passed_time":0.6481648188,"remaining_time":0.06803940087},
{"learn":[3.180741589],"iteration":905,"passed_time":0.6486844476,"remaining_time":0.06730280141},
{"learn":[3.179782639],"iteration":906,"passed_time":0.6492322359,"remaining_time":0.06656956774},
{"learn":[3.176377564],"iteration":907,"passed_time":0.6497623346,"remaining_time":0.0658349502},
{"learn":[3.174078182],"iteration":908,"passed_time":0.650356166,"remaining_time":0.06510716293},
{"learn":[3.171242379],"iteration":909,"passed_time":0.6509753606,"remaining_time":0.06438217852},
{"learn":[3.170421012],"iteration":910,"passed_time":0.6517013618,"remaining_time":0.06366786081},
{"learn":[3.170087224],"iteration":911,"passed_time":0.6522971318,"remaining_time":0.06294095131},
{"learn":[3.167303059],"iteration":912,"passed_time":0.6528558691,"remaining_time":0.06221080023},
{"learn":[3.16705966],"iteration":913,"passed_time":0.6533917369,"remaining_time":0.0614788724},
{"learn":[3.165667683],"iteration":914,"passed_time":0.6539633458,"remaining_time":0.06075069333},
{"learn":[3.164689733],"iteration":915,"passed_time":0.6546032874,"remaining_time":0.06002912243},
{"learn":[3.163311455],"iteration":916,"passed_time":0.6551542194,"remaining_time":0.05929967307},
{"learn":[3.159425016],"iteration":917,"passed_time":0.6557224138,"remaining_time":0.05857215461},
{"learn":[3.159327058],"iteration":918,"passed_time":0.6561947559,"remaining_time":0.05783653452},
{"learn":[3.15819426],"iteration":919,"passed_time":0.6567153725,"remaining_time":0.05710568456},
{"learn":[3.157086603],"iteration":920,"passed_time":0.6572356705,"remaining_time":0.05637526381},
{"learn":[3.153354154],"iteration":921,"passed_time":0.6577456616,"remaining_time":0.05564442691},
{"learn":[3.153261317],"iteration":922,"passed_time":0.6582367153,"remaining_time":0.05491248871},
{"learn":[3.153168454],"iteration":923,"passed_time":0.6587307496,"remaining_time":0.05418131707},
{"learn":[3.152080399],"iteration":924,"passed_time":0.659225202,"remaining_time":0.05345069206},
{"learn":[3.151635144],"iteration":925,"passed_time":0.6597376776,"remaining_time":0.05272201743},
{"learn":[3.147762655],"iteration":926,"passed_time":0.660246602,"remaining_time":0.05199352961},
{"learn":[3.147172317],"iteration":927,"passed_time":0.6607469201,"remaining_time":0.05126484725},
{"learn":[3.146254125],"iteration":928,"passed_time":0.6612582619,"remaining_time":0.05053749903},
{"learn":[3.144869828],"iteration":929,"passed_time":0.661785853,"remaining_time":0.0498118384},
{"learn":[3.143466218],"iteration":930,"passed_time":0.6622912242,"remaining_time":0.04908495647},
{"learn":[3.141919643],"iteration":931,"passed_time":0.6628231313,"remaining_time":0.04836048597},
{"learn":[3.141054135],"iteration":932,"passed_time":0.6633643914,"remaining_time":0.04763709992},
{"learn":[3.139390417],"iteration":933,"passed_time":0.6639048038,"remaining_time":0.04691404395},
{"learn":[3.139025283],"iteration":934,"passed_time":0.6643899914,"remaining_time":0.04618753951},
{"learn":[3.137824183],"iteration":935,"passed_time":0.6649448983,"remaining_time":0.04546631783},
{"learn":[3.135620453],"iteration":936,"passed_time":0.665560641,"remaining_time":0.0447495415},
{"learn":[3.13443178],"iteration":937,"passed_time":0.6662693165,"remaining_time":0.04403912327},
{"learn":[3.132765713],"iteration":938,"passed_time":0.666924638,"remaining_time":0.04332524272},
{"learn":[3.131434124],"iteration":939,"passed_time":0.667546961,"remaining_time":0.04260938049},
{"learn":[3.128384262],"iteration":940,"passed_time":0.6681819844,"remaining_time":0.04189451337},
{"learn":[3.128120455],"iteration":941,"passed_time":0.6687635692,"remaining_time":0.04117652549},
{"learn":[3.126314615],"iteration":942,"passed_time":0.6693124909,"remaining_time":0.04045685258},
{"learn":[3.125409666],"iteration":943,"passed_time":0.669912168,"remaining_time":0.03974055234},
{"learn":[3.123072589],"iteration":944,"passed_time":0.6705268747,"remaining_time":0.03902537366},
{"learn":[3.122921099],"iteration":945,"passed_time":0.6710189291,"remaining_time":0.0383034061},
{"learn":[3.122182662],"iteration":946,"passed_time":0.671568342,"remaining_time":0.03758513424},
{"learn":[3.120040951],"iteration":947,"passed_time":0.6721256398,"remaining_time":0.03686765113},
{"learn":[3.118767799],"iteration":948,"passed_time":0.6726397949,"remaining_time":0.03614818708},
{"learn":[3.118203218],"iteration":949,"passed_time":0.6731630233,"remaining_time":0.03542963281},
{"learn":[3.116343362],"iteration":950,"passed_time":0.6736663318,"remaining_time":0.03471046294},
{"learn":[3.11480829],"iteration":951,"passed_time":0.6741522379,"remaining_time":0.03399086914},
{"learn":[3.112607903],"iteration":952,"passed_time":0.6746711488,"remaining_time":0.03327339349},
{"learn":[3.111661241],"iteration":953,"passed_time":0.6751675035,"remaining_time":0.0325552465},
{"learn":[3.110249676],"iteration":954,"passed_time":0.6756678013,"remaining_time":0.0318377498},
{"learn":[3.107333579],"iteration":955,"passed_time":0.6762805412,"remaining_time":0.03112588265},
{"learn":[3.107149851],"iteration":956,"passed_time":0.6767744107,"remaining_time":0.03040888157},
{"learn":[3.106867336],"iteration":957,"passed_time":0.677281622,"remaining_time":0.02969293124},
{"learn":[3.10364681],"iteration":958,"passed_time":0.6777981428,"remaining_time":0.02897781424},
{"learn":[3.102703811],"iteration":959,"passed_time":0.6783002411,"remaining_time":0.02826251005},
{"learn":[3.101469264],"iteration":960,"passed_time":0.6787994983,"remaining_time":0.02754753427},
{"learn":[3.09863569],"iteration":961,"passed_time":0.6793088283,"remaining_time":0.02683340486},
{"learn":[3.09645939],"iteration":962,"passed_time":0.6798246834,"remaining_time":0.02611995149},
{"learn":[3.096240186],"iteration":963,"passed_time":0.6803368867,"remaining_time":0.0254067717},
{"learn":[3.094838828],"iteration":964,"passed_time":0.6809432126,"remaining_time":0.02469742222},
{"learn":[3.094176802],"iteration":965,"passed_time":0.6816456086,"remaining_time":0.02399166738},
{"learn":[3.093182279],"iteration":966,"passed_time":0.6822040156,"remaining_time":0.0232810057},
{"learn":[3.090150687],"iteration":967,"passed_time":0.6827766841,"remaining_time":0.02257113005},
{"learn":[3.088612829],"iteration":968,"passed_time":0.6833003581,"remaining_time":0.02185997018},
{"learn":[3.087153684],"iteration":969,"passed_time":0.6837822268,"remaining_time":0.02114790392},
{"learn":[3.085866843],"iteration":970,"passed_time":0.6842949042,"remaining_time":0.02043723195},
{"learn":[3.082669094],"iteration":971,"passed_time":0.6848199774,"remaining_time":0.01972732445},
{"learn":[3.081047548],"iteration":972,"passed_time":0.6853346145,"remaining_time":0.01901750729},
{"learn":[3.079684322],"iteration":973,"passed_time":0.685852167,"remaining_time":0.01830816873},
{"learn":[3.07613431],"iteration":974,"passed_time":0.6863533131,"remaining_time":0.0175988029},
{"learn":[3.074005935],"iteration":975,"passed_time":0.6868629211,"remaining_time":0.01689007183},
{"learn":[3.072988853],"iteration":976,"passed_time":0.6873817939,"remaining_time":0.01618196649},
{"learn":[3.072344268],"iteration":977,"passed_time":0.687874017,"remaining_time":0.01547364864},
{"learn":[3.070654438],"iteration":978,"passed_time":0.6883996092,"remaining_time":0.01476648804},
{"learn":[3.069724506],"iteration":979,"passed_time":0.6889083399,"remaining_time":0.01405935388},
{"learn":[3.067763166],"iteration":980,"passed_time":0.6894164606,"remaining_time":0.01335261239},
{"learn":[3.066737893],"iteration":981,"passed_time":0.689929426,"remaining_time":0.01264636422},
{"learn":[3.065248174],"iteration":982,"passed_time":0.6904462842,"remaining_time":0.01194057663},
{"learn":[3.063186837],"iteration":983,"passed_time":0.6909589813,"remaining_time":0.01123510539},
{"learn":[3.062880371],"iteration":984,"passed_time":0.6914836306,"remaining_time":0.01053020757},
{"learn":[3.061288645],"iteration":985,"passed_time":0.6920082956,"remaining_time":0.009825675597},
{"learn":[3.059970575],"iteration":986,"passed_time":0.6925182796,"remaining_time":0.009121314727},
{"learn":[3.059576341],"iteration":987,"passed_time":0.6930342346,"remaining_time":0.008417419853},
{"learn":[3.058175919],"iteration":988,"passed_time":0.6935186344,"remaining_time":0.007713554074},
{"learn":[3.056830702],"iteration":989,"passed_time":0.6940433937,"remaining_time":0.00701053933},
{"learn":[3.056336579],"iteration":990,"passed_time":0.6946094526,"remaining_time":0.006308259408},
{"learn":[3.055810414],"iteration":991,"passed_time":0.6951220616,"remaining_time":0.005605823077},
{"learn":[3.055476518],"iteration":992,"passed_time":0.6956265427,"remaining_time":0.004903711781},
{"learn":[3.053331734],"iteration":993,"passed_time":0.6961826229,"remaining_time":0.004202309595},
{"learn":[3.050890374],"iteration":994,"passed_time":0.6968942563,"remaining_time":0.003501981187},
{"learn":[3.04972623],"iteration":995,"passed_time":0.6974653155,"remaining_time":0.002801065524},
{"learn":[3.047217327],"iteration":996,"passed_time":0.6979964149,"remaining_time":0.002100290115},
{"learn":[3.047155483],"iteration":997,"passed_time":0.6984978318,"remaining_time":0.001399795254},
{"learn":[3.04430671],"iteration":998,"passed_time":0.6990341733,"remaining_time":0.0006997339072},
{"learn":[3.042664195],"iteration":999,"passed_time":0.6995510769,"remaining_time":0}
]}